Workbook

Sheet Portada
B2: PLANTILLA DE EVALUACIÓN DE SEGURIDAD INFORMÁTICA
B3: Modelos MAGERIT y OCTAVE
B4: Universidad Mariano Gálvez de Guatemala — Seguridad de Sistemas Informáticos
B6: Pestaña | C6: Contenido y uso
B7: Inventario_Activos | C7: Registrar los activos de Producción, Pruebas y Desarrollo (hardware, software, datos, RRHH). Completar solo las celdas en amarillo/azul; la Criticidad y Clasificación se calculan solas.
B8: Escalas | C8: Tablas de referencia para las fórmulas (probabilidad, impacto, niveles de riesgo). No modificar.
B9: Riesgos | C9: Registrar mínimo 10 riesgos por activo: Capa de Seguridad por Profundidad, Brecha, Amenaza, Probabilidad e Impacto. El Riesgo MAGERIT, Nivel MAGERIT, Riesgo OCTAVE y Nivel OCTAVE se calculan automáticamente.
B10: Matriz_Calor | C10: Matriz de calor generada automáticamente (Probabilidad x Impacto) a partir de la hoja Riesgos.
B11: Tratamiento | C11: Resumen de tratamiento y priorización por activo, calculado automáticamente desde la hoja Riesgos.
B13: Leyenda de colores
B14: Celda amarilla / texto azul | C14: Campo que el equipo debe llenar
B15: Celda blanca / texto negro | C15: Campo calculado automáticamente por fórmula. No escribir sobre estas celdas.

Sheet Inventario_Activos
A1: No | B1: Ambiente | C1: Tipo de Activo | D1: Nombre del Activo | E1: Responsable | F1: Valor (1-5) | G1: Impacto en el Negocio (1-5) | H1: Confidencialidad (1-5) | I1: Criticidad (calculado) | J1: Clasificación (calculado)
A2: 1 | B2: Producción | C2: Hardware | D2: Servidor de Base de Datos | E2: Danny | F2: 4 | G2: 5 | H2: 5 | I2: =ROUND(AVERAGE(F2:H2),0) -> 5 | J2: =INDEX(Escalas!$B$10:$B$13,MATCH(I2,Escalas!$A$10:$A$13,1)) -> Alta
A3: 2 | B3: Producción | C3: Software | D3: Sistema ERP / Facturación | E3: Javier | F3: 3 | G3: 3 | H3: 3 | I3: =ROUND(AVERAGE(F3:H3),0) -> 3 | J3: =INDEX(Escalas!$B$10:$B$13,MATCH(I3,Escalas!$A$10:$A$13,1)) -> Media
A4: 3 | B4: Producción | C4: Datos | D4: Datos de clientes | E4: Katherin | F4: 3 | G4: 3 | H4: 3 | I4: =ROUND(AVERAGE(F4:H4),0) -> 3 | J4: =INDEX(Escalas!$B$10:$B$13,MATCH(I4,Escalas!$A$10:$A$13,1)) -> Media
A5: 4 | B5: Producción | C5: Recursos Humanos | D5: Administrador de sistemas | E5: Josue | F5: 3 | G5: 3 | H5: 3 | I5: =ROUND(AVERAGE(F5:H5),0) -> 3 | J5: =INDEX(Escalas!$B$10:$B$13,MATCH(I5,Escalas!$A$10:$A$13,1)) -> Media
A6: 5 | B6: Producción | C6: Hardware | D6: Firewall / Router de borde | E6: Diancarlo | F6: 3 | G6: 3 | H6: 3 | I6: =ROUND(AVERAGE(F6:H6),0) -> 3 | J6: =INDEX(Escalas!$B$10:$B$13,MATCH(I6,Escalas!$A$10:$A$13,1)) -> Media
A7: 6 | B7: Pruebas | C7: Hardware | D7: Servidor de pruebas | E7: Danny | F7: 3 | G7: 3 | H7: 3 | I7: =ROUND(AVERAGE(F7:H7),0) -> 3 | J7: =INDEX(Escalas!$B$10:$B$13,MATCH(I7,Escalas!$A$10:$A$13,1)) -> Media
A8: 7 | B8: Pruebas | C8: Software | D8: Ambiente de staging web | E8: Javier | F8: 3 | G8: 3 | H8: 3 | I8: =ROUND(AVERAGE(F8:H8),0) -> 3 | J8: =INDEX(Escalas!$B$10:$B$13,MATCH(I8,Escalas!$A$10:$A$13,1)) -> Media
A9: 8 | B9: Pruebas | C9: Datos | D9: Datos de prueba anonimizados | E9: Katherin | F9: 3 | G9: 3 | H9: 3 | I9: =ROUND(AVERAGE(F9:H9),0) -> 3 | J9: =INDEX(Escalas!$B$10:$B$13,MATCH(I9,Escalas!$A$10:$A$13,1)) -> Media
A10: 9 | B10: Pruebas | C10: Recursos Humanos | D10: QA Tester | E10: Josue | F10: 3 | G10: 3 | H10: 3 | I10: =ROUND(AVERAGE(F10:H10),0) -> 3 | J10: =INDEX(Escalas!$B$10:$B$13,MATCH(I10,Escalas!$A$10:$A$13,1)) -> Media
A11: 10 | B11: Pruebas | C11: Software | D11: Herramienta de automatización de pruebas | E11: Diancarlo | F11: 3 | G11: 3 | H11: 3 | I11: =ROUND(AVERAGE(F11:H11),0) -> 3 | J11: =INDEX(Escalas!$B$10:$B$13,MATCH(I11,Escalas!$A$10:$A$13,1)) -> Media
A12: 11 | B12: Desarrollo | C12: Hardware | D12: Estación de trabajo del desarrollador | E12: Danny | F12: 3 | G12: 3 | H12: 3 | I12: =ROUND(AVERAGE(F12:H12),0) -> 3 | J12: =INDEX(Escalas!$B$10:$B$13,MATCH(I12,Escalas!$A$10:$A$13,1)) -> Media
A13: 12 | B13: Desarrollo | C13: Software | D13: Repositorio de código (Git) | E13: Javier | F13: 3 | G13: 3 | H13: 3 | I13: =ROUND(AVERAGE(F13:H13),0) -> 3 | J13: =INDEX(Escalas!$B$10:$B$13,MATCH(I13,Escalas!$A$10:$A$13,1)) -> Media
... A16: 15 | B16: Desarrollo | C16: Software | D16: Entorno IDE / CI-CD | E16: Diancarlo | F16: 3 | G16: 3 | H16: 3 | I16: =ROUND(AVERAGE(F16:H16),0) -> 3 | J16: =INDEX(Escalas!$B$10:$B$13,MATCH(I16,Escalas!$A$10:$A$13,1)) -> Media
B18: Nota: Valor, Impacto en el Negocio y Confidencialidad se califican de 1 (muy bajo) a 5 (muy alto). La Criticidad es el promedio redondeado de esas 3 columnas.

Sheet Riesgos
A1: No | B1: Ambiente | C1: Tipo de Activo | D1: Activo | E1: Capa de Seguridad por Profundidad | F1: Brecha | G1: Amenaza | H1: Probabilidad (1-5) | I1: Impacto (1-5) | J1: Riesgo MAGERIT | K1: Nivel MAGERIT | L1: Criticidad del Activo | M1: Riesgo OCTAVE | N1: Nivel OCTAVE | O1: Tratamiento | P1: Solución / Control propuesto | Q1: Clave_Rank (auxiliar, no borrar)
A2: 1 | B2: =Inventario_Activos!B2 -> Producción | C2: =Inventario_Activos!C2 -> Hardware | D2: =Inventario_Activos!D2 -> Servidor de Base de Datos | E2: Seguridad Física | F2: Acceso no autorizado al cuarto de servidores | G2: Robo o sabotaje de hardware | H2: 2 | I2: 5 | J2: =H2*I2 -> 10 | K2: =INDEX(Escalas!$F$2:$F$5,MATCH(J2,Escalas!$E$2:$E$5,1)) -> Moderado | L2: =INDEX(Inventario_Activos!$I$2:$I$16,MATCH(D2,Inventario_Activos!$D$2:$D$16,0)) -> 5 | M2: =ROUND(J2*L2/5,0) -> 10 | N2: =INDEX(Escalas!$F$2:$F$5,MATCH(M2,Escalas!$E$2:$E$5,1)) -> Moderado | O2: Reducir/Mitigar | P2: Control de acceso biométrico y CCTV en el cuarto de servidores, con bitácora de ingreso. | Q2: =J2+(152-ROW())/100000 -> 10.0015
A3: 2 | B3: =Inventario_Activos!B2 -> Producción | C3: =Inventario_Activos!C2 -> Hardware | D3: =Inventario_Activos!D2 -> Servidor de Base de Datos | E3: Seguridad de Red | F3: Puertos de administración expuestos a la red interna | G3: Acceso remoto no autorizado | H3: 3 | I3: 5 | J3: =H3*I3 -> 15 | K3: =INDEX(Escalas!$F$2:$F$5,MATCH(J3,Escalas!$E$2:$E$5,1)) -> Alto | L3: =INDEX(Inventario_Activos!$I$2:$I$16,MATCH(D3,Inventario_Activos!$D$2:$D$16,0)) -> 5 | M3: =ROUND(J3*L3/5,0) -> 15 | N3: =INDEX(Escalas!$F$2:$F$5,MATCH(M3,Escalas!$E$2:$E$5,1)) -> Alto | O3: Reducir/Mitigar | P3: Segmentar la red de administración (VLAN dedicada) y exigir VPN + MFA para acceso remoto. | Q3: =J3+(152-ROW())/100000 -> 15.00149
A4: 3 | B4: =Inventario_Activos!B2 -> Producción | C4: =Inventario_Activos!C2 -> Hardware | D4: =Inventario_Activos!D2 -> Servidor de Base de Datos | E4: Seguridad de Host | F4: Sistema operativo del servidor desactualizado | G4: Explotación de vulnerabilidades conocidas | H4: 4 | I4: 4 | J4: =H4*I4 -> 16 | K4: =INDEX(Escalas!$F$2:$F$5,MATCH(J4,Escalas!$E$2:$E$5,1)) -> Alto | L4: =INDEX(Inventario_Activos!$I$2:$I$16,MATCH(D4,Inventario_Activos!$D$2:$D$16,0)) -> 5 | M4: =ROUND(J4*L4/5,0) -> 16 | N4: =INDEX(Escalas!$F$2:$F$5,MATCH(M4,Escalas!$E$2:$E$5,1)) -> Alto | O4: Reducir/Mitigar | P4: Gestión de parches automatizada y hardening del sistema operativo del servidor. | Q4: =J4+(152-ROW())/100000 -> 16.00148
A5: 4 | B5: =Inventario_Activos!B2 -> Producción | C5: =Inventario_Activos!C2 -> Hardware | D5: =Inventario_Activos!D2 -> Servidor de Base de Datos | E5: Seguridad de Aplicación | F5: Motor de base de datos con configuración por defecto | G5: Inyección SQL / escalamiento de privilegios | H5: 3 | I5: 5 | J5: =H5*I5 -> 15 | K5: =INDEX(Escalas!$F$2:$F$5,MATCH(J5,Escalas!$E$2:$E$5,1)) -> Alto | L5: =INDEX(Inventario_Activos!$I$2:$I$16,MATCH(D5,Inventario_Activos!$D$2:$D$16,0)) -> 5 | M5: =ROUND(J5*L5/5,0) -> 15 | N5: =INDEX(Escalas!$F$2:$F$5,MATCH(M5,Escalas!$E$2:$E$5,1)) -> Alto | O5: Reducir/Mitigar | P5: Validación de entradas, consultas parametrizadas y bastionado del motor de base de datos. | Q5: =J5+(152-ROW())/100000 -> 15.00147
A6: 5 | B6: =Inventario_Activos!B2 -> Producción | C6: =Inventario_Activos!C2 -> Hardware | D6: =Inventario_Activos!D2 -> Servidor de Base de Datos | E6: Seguridad de Datos | F6: Ausencia de cifrado en datos en reposo | G6: Fuga de información confidencial | H6: 3 | I6: 5 | J6: =H6*I6 -> 15 | K6: =INDEX(Escalas!$F$2:$F$5,MATCH(J6,Escalas!$E$2:$E$5,1)) -> Alto | L6: =INDEX(Inventario_Activos!$I$2:$I$16,MATCH(D6,Inventario_Activos!$D$2:$D$16,0)) -> 5 | M6: =ROUND(J6*L6/5,0) -> 15 | N6: =INDEX(Escalas!$F$2:$F$5,MATCH(M6,Escalas!$E$2:$E$5,1)) -> Alto | O6: Reducir/Mitigar | P6: Cifrar los datos en reposo (TDE) y en tránsito (TLS). | Q6: =J6+(152-ROW())/100000 -> 15.00146
A7: 6 | B7: =Inventario_Activos!B2 -> Producción | C7: =Inventario_Activos!C2 -> Hardware | D7: =Inventario_Activos!D2 -> Servidor de Base de Datos | E7: Gestión de Identidad y Acceso | F7: Cuentas de administrador compartidas | G7: Uso indebido de credenciales privilegiadas | H7: 3 | I7: 4 | J7: =H7*I7 -> 12 | K7: =INDEX(Escalas!$F$2:$F$5,MATCH(J7,Escalas!$E$2:$E$5,1)) -> Alto | L7: =INDEX(Inventario_Activos!$I$2:$I$16,MATCH(D7,Inventario_Activos!$D$2:$D$16,0)) -> 5 | M7: =ROUND(J7*L7/5,0) -> 12 | N7: =INDEX(Escalas!$F$2:$F$5,MATCH(M7,Escalas!$E$2:$E$5,1)) -> Alto | O7: Reducir/Mitigar | P7: Cuentas nominales, mínimo privilegio y bóveda de contraseñas (PAM). | Q7: =J7+(152-ROW())/100000 -> 12.00145
A8: 7 | B8: =Inventario_Activos!B2 -> Producción | C8: =Inventario_Activos!C2 -> Hardware | D8: =Inventario_Activos!D2 -> Servidor de Base de Datos | E8: Monitoreo y Respuesta | F8: Falta de registro (logging) centralizado | G8: Detección tardía de incidentes | H8: 3 | I8: 3 | J8: =H8*I8 -> 9 | K8: =INDEX(Escalas!$F$2:$F$5,MATCH(J8,Escalas!$E$2:$E$5,1)) -> Moderado | L8: =INDEX(Inventario_Activos!$I$2:$I$16,MATCH(D8,Inventario_Activos!$D$2:$D$16,0)) -> 5 | M8: =ROUND(J8*L8/5,0) -> 9 | N8: =INDEX(Escalas!$F$2:$F$5,MATCH(M8,Escalas!$E$2:$E$5,1)) -> Moderado | O8: Reducir/Mitigar | P8: Centralizar logs en un SIEM con alertas en tiempo real. | Q8: =J8+(152-ROW())/100000 -> 9.00144
A9: 8 | B9: =Inventario_Activos!B2 -> Producción | C9: =Inventario_Activos!C2 -> Hardware | D9: =Inventario_Activos!D2 -> Servidor de Base de Datos | E9: Continuidad y Respaldo | F9: Respaldos no probados periódicamente | G9: Pérdida de datos ante fallo o ataque | H9: 2 | I9: 5 | J9: =H9*I9 -> 10 | K9: =INDEX(Escalas!$F$2:$F$5,MATCH(J9,Escalas!$E$2:$E$5,1)) -> Moderado | L9: =INDEX(Inventario_Activos!$I$2:$I$16,MATCH(D9,Inventario_Activos!$D$2:$D$16,0)) -> 5 | M9: =ROUND(J9*L9/5,0) -> 10 | N9: =INDEX(Escalas!$F$2:$F$5,MATCH(M9,Escalas!$E$2:$E$5,1)) -> Moderado | O9: Reducir/Mitigar | P9: Plan de respaldo 3-2-1 con pruebas periódicas de restauración. | Q9: =J9+(152-ROW())/100000 -> 10.00143
A10: 9 | B10: =Inventario_Activos!B2 -> Producción | C10: =Inventario_Activos!C2 -> Hardware | D10: =Inventario_Activos!D2 -> Servidor de Base de Datos | E10: Seguridad Perimetral | F10: Reglas de firewall obsoletas o permisivas | G10: Movimiento lateral de un atacante | H10: 3 | I10: 4 | J10: =H10*I10 -> 12 | K10: =INDEX(Escalas!$F$2:$F$5,MATCH(J10,Escalas!$E$2:$E$5,1)) -> Alto | L10: =INDEX(Inventario_Activos!$I$2:$I$16,MATCH(D10,Inventario_Activos!$D$2:$D$16,0)) -> 5 | M10: =ROUND(J10*L10/5,0) -> 12 | N10: =INDEX(Escalas!$F$2:$F$5,MATCH(M10,Escalas!$E$2:$E$5,1)) -> Alto | O10: Reducir/Mitigar | P10: Revisar y depurar reglas de firewall; segmentación/microsegmentación de red. | Q10: =J10+(152-ROW())/100000 -> 12.00142
A11: 10 | B11: =Inventario_Activos!B2 -> Producción | C11: =Inventario_Activos!C2 -> Hardware | D11: =Inventario_Activos!D2 -> Servidor de Base de Datos | E11: Concientización y Procesos | F11: Falta de procedimiento de gestión de parches | G11: Explotación de vulnerabilidades no corregidas | H11: 4 | I11: 4 | J11: =H11*I11 -> 16 | K11: =INDEX(Escalas!$F$2:$F$5,MATCH(J11,Escalas!$E$2:$E$5,1)) -> Alto | L11: =INDEX(Inventario_Activos!$I$2:$I$16,MATCH(D11,Inventario_Activos!$D$2:$D$16,0)) -> 5 | M11: =ROUND(J11*L11/5,0) -> 16 | N11: =INDEX(Escalas!$F$2:$F$5,MATCH(M11,Escalas!$E$2:$E$5,1)) -> Alto | O11: Reducir/Mitigar | P11: Proceso formal de gestión de parches con SLA de aplicación. | Q11: =J11+(152-ROW())/100000 -> 16.00141
A12: 11 | B12: =Inventario_Activos!B3 -> Producción | C12: =Inventario_Activos!C3 -> Software | D12: =Inventario_Activos!D3 -> Sistema ERP / Facturación | E12: Seguridad Física | F12: Servidores del ERP alojados sin control de acceso físico restringido | G12: Acceso físico no autorizado al hardware que aloja el ERP | H12: 2 | I12: 4 | J12: =H12*I12 -> 8 | K12: =INDEX(Escalas!$F$2:$F$5,MATCH(J12,Escalas!$E$2:$E$5,1)) -> Moderado | L12: =INDEX(Inventario_Activos!$I$2:$I$16,MATCH(D12,Inventario_Activos!$D$2:$D$16,0)) -> 3 | M12: =ROUND(J12*L12/5,0) -> 5 | N12: =INDEX(Escalas!$F$2:$F$5,MATCH(M12,Escalas!$E$2:$E$5,1)) -> Bajo | O12: Reducir/Mitigar | P12: Alojar el servidor en centro de datos con control de acceso y video vigilancia. | Q12: =J12+(152-ROW())/100000 -> 8.0014
A13: 12 | B13: =Inventario_Activos!B3 -> Producción | C13: =Inventario_Activos!C3 -> Software | D13: =Inventario_Activos!D3 -> Sistema ERP / Facturación | E13: Seguridad de Red | F13: Comunicación del ERP sin cifrado entre módulos | G13: Intercepción de tráfico (sniffing) | H13: 3 | I13: 4 | J13: =H13*I13 -> 12 | K13: =INDEX(Escalas!$F$2:$F$5,MATCH(J13,Escalas!$E$2:$E$5,1)) -> Alto | L13: =INDEX(Inventario_Activos!$I$2:$I$16,MATCH(D13,Inventario_Activos!$D$2:$D$16,0)) -> 3 | M13: =ROUND(J13*L13/5,0) -> 7 | N13: =INDEX(Escalas!$F$2:$F$5,MATCH(M13,Escalas!$E$2:$E$5,1)) -> Moderado | O13: Reducir/Mitigar | P13: Cifrar comunicaciones internas con TLS y segmentar la red del ERP. | Q13: =J13+(152-ROW())/100000 -> 12.00139
A14: 13 | B14: =Inventario_Activos!B3 -> Producción | C14: =Inventario_Activos!C3 -> Software | D14: =Inventario_Activos!D3 -> Sistema ERP / Facturación | E14: Seguridad de Host | F14: Servidor de aplicaciones del ERP sin actualizaciones de seguridad | G14: Explotación de vulnerabilidades del sistema operativo | H14: 3 | I14: 4 | J14: =H14*I14 -> 12 | K14: =INDEX(Escalas!$F$2:$F$5,MATCH(J14,Escalas!$E$2:$E$5,1)) -> Alto | L14: =INDEX(Inventario_Activos!$I$2:$I$16,MATCH(D14,Inventario_Activos!$D$2:$D$16,0)) -> 3 | M14: =ROUND(J14*L14/5,0) -> 7 | N14: =INDEX(Escalas!$F$2:$F$5,MATCH(M14,Escalas!$E$2:$E$5,1)) -> Moderado | O14: Reducir/Mitigar | P14: Ciclo de actualización mensual y bastionado del servidor. | Q14: =J14+(152-ROW())/100000 -> 12.00138
A15: 14 | B15: =Inventario_Activos!B3 -> Producción | C15: =Inventario_Activos!C3 -> Software | D15: =Inventario_Activos!D3 -> Sistema ERP / Facturación | E15: Seguridad de Aplicación | F15: Módulo de facturación sin validación de entradas | G15: Inyección de código / manipulación de transacciones | H15: 3 | I15: 5 | J15: =H15*I15 -> 15 | K15: =INDEX(Escalas!$F$2:$F$5,MATCH(J15,Escalas!$E$2:$E$5,1)) -> Alto | L15: =INDEX(Inventario_Activos!$I$2:$I$16,MATCH(D15,Inventario_Activos!$D$2:$D$16,0)) -> 3 | M15: =ROUND(J15*L15/5,0) -> 9 | N15: =INDEX(Escalas!$F$2:$F$5,MATCH(M15,Escalas!$E$2:$E$5,1)) -> Moderado | O15: Reducir/Mitigar | P15: Pruebas de seguridad de aplicaciones (SAST/DAST) antes de cada release. | Q15: =J15+(152-ROW())/100000 -> 15.00137
A16: 15 | B16: =Inventario_Activos!B3 -> Producción | C16: =Inventario_Activos!C3 -> Software | D16: =Inventario_Activos!D3 -> Sistema ERP / Facturación | E16: Seguridad de Datos | F16: Base de datos del ERP sin cifrado de campos sensibles (montos, NIT) | G16: Exposición de información financiera | H16: 2 | I16: 5 | J16: =H16*I16 -> 10 | K16: =INDEX(Escalas!$F$2:$F$5,MATCH(J16,Escalas!$E$2:$E$5,1)) -> Moderado | L16: =INDEX(Inventario_Activos!$I$2:$I$16,MATCH(D16,Inventario_Activos!$D$2:$D$16,0)) -> 3 | M16: =ROUND(J16*L16/5,0) -> 6 | N16: =INDEX(Escalas!$F$2:$F$5,MATCH(M16,Escalas!$E$2:$E$5,1)) -> Moderado | O16: Reducir/Mitigar | P16: Cifrar campos sensibles y enmascarar datos en reportes. | Q16: =J16+(152-ROW())/100000 -> 10.00136
A17: 16 | B17: =Inventario_Activos!B3 -> Producción | C17: =Inventario_Activos!C3 -> Software | D17: =Inventario_Activos!D3 -> Sistema ERP / Facturación | E17: Gestión de Identidad y Acceso | F17: Roles del ERP mal configurados (usuarios con permisos excesivos) | G17: Fraude interno o modificación indebida de facturas | H17: 3 | I17: 5 | J17: =H17*I17 -> 15 | K17: =INDEX(Escalas!$F$2:$F$5,MATCH(J17,Escalas!$E$2:$E$5,1)) -> Alto | L17: =INDEX(Inventario_Activos!$I$2:$I$16,MATCH(D17,Inventario_Activos!$D$2:$D$16,0)) -> 3 | M17: =ROUND(J17*L17/5,0) -> 9 | N17: =INDEX(Escalas!$F$2:$F$5,MATCH(M17,Escalas!$E$2:$E$5,1)) -> Moderado | O17: Reducir/Mitigar | P17: Revisión periódica de roles y segregación de funciones (SoD). | Q17: =J17+(152-ROW())/100000 -> 15.00135
A18: 17 | B18: =Inventario_Activos!B3 -> Producción | C18: =Inventario_Activos!C3 -> Software | D18: =Inventario_Activos!D3 -> Sistema ERP / Facturación | E18: Monitoreo y Respuesta | F18: Ausencia de alertas ante transacciones inusuales | G18: Fraude no detectado a tiempo | H18: 3 | I18: 4 | J18: =H18*I18 -> 12 | K18: =INDEX(Escalas!$F$2:$F$5,MATCH(J18,Escalas!$E$2:$E$5,1)) -> Alto | L18: =INDEX(Inventario_Activos!$I$2:$I$16,MATCH(D18,Inventario_Activos!$D$2:$D$16,0)) -> 3 | M18: =ROUND(J18*L18/5,0) -> 7 | N18: =INDEX(Escalas!$F$2:$F$5,MATCH(M18,Escalas!$E$2:$E$5,1)) -> Moderado | O18: Reducir/Mitigar | P18: Reglas de auditoría y alertas de transacciones atípicas. | Q18: =J18+(152-ROW())/100000 -> 12.00134
A19: 18 | B19: =Inventario_Activos!B3 -> Producción | C19: =Inventario_Activos!C3 -> Software | D19: =Inventario_Activos!D3 -> Sistema ERP / Facturación | E19: Continuidad y Respaldo | F19: Backup del ERP solo en sitio, sin copia externa | G19: Pérdida de información contable ante desastre | H19: 2 | I19: 5 | J19: =H19*I19 -> 10 | K19: =INDEX(Escalas!$F$2:$F$5,MATCH(J19,Escalas!$E$2:$E$5,1)) -> Moderado | L19: =INDEX(Inventario_Activos!$I$2:$I$16,MATCH(D19,Inventario_Activos!$D$2:$D$16,0)) -> 3 | M19: =ROUND(J19*L19/5,0) -> 6 | N19: =INDEX(Escalas!$F$2:$F$5,MATCH(M19,Escalas!$E$2:$E$5,1)) -> Moderado | O19: Reducir/Mitigar | P19: Respaldo en la nube con retención definida y prueba de restauración. | Q19: =J19+(152-ROW())/100000 -> 10.00133
A20: 19 | B20: =Inventario_Activos!B3 -> Producción | C20: =Inventario_Activos!C3 -> Software | D20: =Inventario_Activos!D3 -> Sistema ERP / Facturación | E20: Seguridad Perimetral | F20: Puerto de administración del ERP expuesto a internet | G20: Acceso externo no autorizado a la consola de administración | H20: 3 | I20: 4 | J20: =H20*I20 -> 12 | K20: =INDEX(Escalas!$F$2:$F$5,MATCH(J20,Escalas!$E$2:$E$5,1)) -> Alto | L20: =INDEX(Inventario_Activos!$I$2:$I$16,MATCH(D20,Inventario_Activos!$D$2:$D$16,0)) -> 3 | M20: =ROUND(J20*L20/5,0) -> 7 | N20: =INDEX(Escalas!$F$2:$F$5,MATCH(M20,Escalas!$E$2:$E$5,1)) -> Moderado | O20: Reducir/Mitigar | P20: Restringir el acceso administrativo a IPs internas mediante firewall/VPN. | Q20: =J20+(152-ROW())/100000 -> 12.00132
A21: 20 | B21: =Inventario_Activos!B3 -> Producción | C21: =Inventario_Activos!C3 -> Software | D21: =Inventario_Activos!D3 -> Sistema ERP / Facturación | E21: Concientización y Procesos | F21: Falta de capacitación a usuarios sobre manejo del ERP | G21: Errores de captura y fraude por desconocimiento | H21: 3 | I21: 3 | J21: =H21*I21 -> 9 | K21: =INDEX(Escalas!$F$2:$F$5,MATCH(J21,Escalas!$E$2:$E$5,1)) -> Moderado | L21: =INDEX(Inventario_Activos!$I$2:$I$16,MATCH(D21,Inventario_Activos!$D$2:$D$16,0)) -> 3 | M21: =ROUND(J21*L21/5,0) -> 5 | N21: =INDEX(Escalas!$F$2:$F$5,MATCH(M21,Escalas!$E$2:$E$5,1)) -> Bajo | O21: Reducir/Mitigar | P21: Capacitación periódica y manual de procedimientos de uso. | Q21: =J21+(152-ROW())/100000 -> 9.00131
A22: 21 | B22: =Inventario_Activos!B4 -> Producción | C22: =Inventario_Activos!C4 -> Datos | D22: =Inventario_Activos!D4 -> Datos de clientes | E22: Seguridad Física | F22: Medios de respaldo con datos de clientes almacenados sin resguardo físico | G22: Robo o pérdida de medios de respaldo | H22: 2 | I22: 5 | J22: =H22*I22 -> 10 | K22: =INDEX(Escalas!$F$2:$F$5,MATCH(J22,Escalas!$E$2:$E$5,1)) -> Moderado | L22: =INDEX(Inventario_Activos!$I$2:$I$16,MATCH(D22,Inventario_Activos!$D$2:$D$16,0)) -> 3 | M22: =ROUND(J22*L22/5,0) -> 6 | N22: =INDEX(Escalas!$F$2:$F$5,MATCH(M22,Escalas!$E$2:$E$5,1)) -> Moderado | O22: Reducir/Mitigar | P22: Resguardo en caja fuerte o custodia externa certificada. | Q22: =J22+(152-ROW())/100000 -> 10.0013
A23: 22 | B23: =Inventario_Activos!B4 -> Producción | C23: =Inventario_Activos!C4 -> Datos | D23: =Inventario_Activos!D4 -> Datos de clientes | E23: Seguridad de Red | F23: Transferencia de datos de clientes entre sistemas sin cifrado | G23: Intercepción de información personal en tránsito | H23: 3 | I23: 5 | J23: =H23*I23 -> 15 | K23: =INDEX(Escalas!$F$2:$F$5,MATCH(J23,Escalas!$E$2:$E$5,1)) -> Alto | L23: =INDEX(Inventario_Activos!$I$2:$I$16,MATCH(D23,Inventario_Activos!$D$2:$D$16,0)) -> 3 | M23: =ROUND(J23*L23/5,0) -> 9 | N23: =INDEX(Escalas!$F$2:$F$5,MATCH(M23,Escalas!$E$2:$E$5,1)) -> Moderado | O23: Reducir/Mitigar | P23: Cifrado TLS obligatorio en todas las transferencias de datos. | Q23: =J23+(152-ROW())/100000 -> 15.00129
A24: 23 | B24: =Inventario_Activos!B4 -> Producción | C24: =Inventario_Activos!C4 -> Datos | D24: =Inventario_Activos!D4 -> Datos de clientes | E24: Seguridad de Host | F24: Base de datos de clientes en servidor sin bastionado específico | G24: Compromiso del servidor que aloja los datos | H24: 3 | I24: 5 | J24: =H24*I24 -> 15 | K24: =INDEX(Escalas!$F$2:$F$5,MATCH(J24,Escalas!$E$2:$E$5,1)) -> Alto | L24: =INDEX(Inventario_Activos!$I$2:$I$16,MATCH(D24,Inventario_Activos!$D$2:$D$16,0)) -> 3 | M24: =ROUND(J24*L24/5,0) -> 9 | N24: =INDEX(Escalas!$F$2:$F$5,MATCH(M24,Escalas!$E$2:$E$5,1)) -> Moderado | O24: Reducir/Mitigar | P24: Hardening del servidor de base de datos y monitoreo de integridad. | Q24: =J24+(152-ROW())/100000 -> 15.00128
A25: 24 | B25: =Inventario_Activos!B4 -> Producción | C25: =Inventario_Activos!C4 -> Datos | D25: =Inventario_Activos!D4 -> Datos de clientes | E25: Seguridad de Aplicación | F25: Aplicaciones con acceso directo a la base de datos sin capa de control | G25: Exfiltración de datos mediante consultas no controladas | H25: 3 | I25: 5 | J25: =H25*I25 -> 15 | K25: =INDEX(Escalas!$F$2:$F$5,MATCH(J25,Escalas!$E$2:$E$5,1)) -> Alto | L25: =INDEX(Inventario_Activos!$I$2:$I$16,MATCH(D25,Inventario_Activos!$D$2:$D$16,0)) -> 3 | M25: =ROUND(J25*L25/5,0) -> 9 | N25: =INDEX(Escalas!$F$2:$F$5,MATCH(M25,Escalas!$E$2:$E$5,1)) -> Moderado | O25: Reducir/Mitigar | P25: Implementar capa de API con control de acceso y limitación de consultas. | Q25: =J25+(152-ROW())/100000 -> 15.00127
A26: 25 | B26: =Inventario_Activos!B4 -> Producción | C26: =Inventario_Activos!C4 -> Datos | D26: =Inventario_Activos!D4 -> Datos de clientes | E26: Seguridad de Datos | F26: Datos personales sin cifrado ni enmascaramiento | G26: Fuga de información personal (incumplimiento normativo) | H26: 3 | I26: 5 | J26: =H26*I26 -> 15 | K26: =INDEX(Escalas!$F$2:$F$5,MATCH(J26,Escalas!$E$2:$E$5,1)) -> Alto | L26: =INDEX(Inventario_Activos!$I$2:$I$16,MATCH(D26,Inventario_Activos!$D$2:$D$16,0)) -> 3 | M26: =ROUND(J26*L26/5,0) -> 9 | N26: =INDEX(Escalas!$F$2:$F$5,MATCH(M26,Escalas!$E$2:$E$5,1)) -> Moderado | O26: Reducir/Mitigar | P26: Cifrado de campos sensibles y clasificación de datos personales. | Q26: =J26+(152-ROW())/100000 -> 15.00126
A27: 26 | B27: =Inventario_Activos!B4 -> Producción | C27: =Inventario_Activos!C4 -> Datos | D27: =Inventario_Activos!D4 -> Datos de clientes | E27: Gestión de Identidad y Acceso | F27: Múltiples roles con acceso de lectura/escritura a todos los datos de clientes | G27: Acceso indebido o excesivo a información personal | H27: 3 | I27: 5 | J27: =H27*I27 -> 15 | K27: =INDEX(Escalas!$F$2:$F$5,MATCH(J27,Escalas!$E$2:$E$5,1)) -> Alto | L27: =INDEX(Inventario_Activos!$I$2:$I$16,MATCH(D27,Inventario_Activos!$D$2:$D$16,0)) -> 3 | M27: =ROUND(J27*L27/5,0) -> 9 | N27: =INDEX(Escalas!$F$2:$F$5,MATCH(M27,Escalas!$E$2:$E$5,1)) -> Moderado | O27: Reducir/Mitigar | P27: Control de acceso basado en roles con mínimo privilegio. | Q27: =J27+(152-ROW())/100000 -> 15.00125
A28: 27 | B28: =Inventario_Activos!B4 -> Producción | C28: =Inventario_Activos!C4 -> Datos | D28: =Inventario_Activos!D4 -> Datos de clientes | E28: Monitoreo y Respuesta | F28: Sin auditoría de consultas a datos sensibles de clientes | G28: Acceso indebido no detectado | H28: 3 | I28: 4 | J28: =H28*I28 -> 12 | K28: =INDEX(Escalas!$F$2:$F$5,MATCH(J28,Escalas!$E$2:$E$5,1)) -> Alto | L28: =INDEX(Inventario_Activos!$I$2:$I$16,MATCH(D28,Inventario_Activos!$D$2:$D$16,0)) -> 3 | M28: =ROUND(J28*L28/5,0) -> 7 | N28: =INDEX(Escalas!$F$2:$F$5,MATCH(M28,Escalas!$E$2:$E$5,1)) -> Moderado | O28: Reducir/Mitigar | P28: Auditoría de accesos a datos sensibles (Database Activity Monitoring). | Q28: =J28+(152-ROW())/100000 -> 12.00124
A29: 28 | B29: =Inventario_Activos!B4 -> Producción | C29: =Inventario_Activos!C4 -> Datos | D29: =Inventario_Activos!D4 -> Datos de clientes | E29: Continuidad y Respaldo | F29: Respaldos de datos de clientes sin cifrado | G29: Exposición de datos personales ante robo de respaldo | H29: 2 | I29: 5 | J29: =H29*I29 -> 10 | K29: =INDEX(Escalas!$F$2:$F$5,MATCH(J29,Escalas!$E$2:$E$5,1)) -> Moderado | L29: =INDEX(Inventario_Activos!$I$2:$I$16,MATCH(D29,Inventario_Activos!$D$2:$D$16,0)) -> 3 | M29: =ROUND(J29*L29/5,0) -> 6 | N29: =INDEX(Escalas!$F$2:$F$5,MATCH(M29,Escalas!$E$2:$E$5,1)) -> Moderado | O29: Reducir/Mitigar | P29: Cifrado de respaldos y control de acceso a los mismos. | Q29: =J29+(152-ROW())/100000 -> 10.00123
A30: 29 | B30: =Inventario_Activos!B4 -> Producción | C30: =Inventario_Activos!C4 -> Datos | D30: =Inventario_Activos!D4 -> Datos de clientes | E30: Seguridad Perimetral | F30: Exportaciones masivas de datos permitidas sin control | G30: Exfiltración masiva de datos de clientes | H30: 2 | I30: 5 | J30: =H30*I30 -> 10 | K30: =INDEX(Escalas!$F$2:$F$5,MATCH(J30,Escalas!$E$2:$E$5,1)) -> Moderado | L30: =INDEX(Inventario_Activos!$I$2:$I$16,MATCH(D30,Inventario_Activos!$D$2:$D$16,0)) -> 3 | M30: =ROUND(J30*L30/5,0) -> 6 | N30: =INDEX(Escalas!$F$2:$F$5,MATCH(M30,Escalas!$E$2:$E$5,1)) -> Moderado | O30: Reducir/Mitigar | P30: Limitar y auditar las exportaciones masivas de datos (DLP). | Q30: =J30+(152-ROW())/100000 -> 10.00122
A31: 30 | B31: =Inventario_Activos!B4 -> Producción | C31: =Inventario_Activos!C4 -> Datos | D31: =Inventario_Activos!D4 -> Datos de clientes | E31: Concientización y Procesos | F31: Falta de política de protección de datos personales | G31: Manejo inadecuado de datos por parte del personal | H31: 3 | I31: 4 | J31: =H31*I31 -> 12 | K31: =INDEX(Escalas!$F$2:$F$5,MATCH(J31,Escalas!$E$2:$E$5,1)) -> Alto | L31: =INDEX(Inventario_Activos!$I$2:$I$16,MATCH(D31,Inventario_Activos!$D$2:$D$16,0)) -> 3 | M31: =ROUND(J31*L31/5,0) -> 7 | N31: =INDEX(Escalas!$F$2:$F$5,MATCH(M31,Escalas!$E$2:$E$5,1)) -> Moderado | O31: Reducir/Mitigar | P31: Política de protección de datos y capacitación en normativa aplicable. | Q31: =J31+(152-ROW())/100000 -> 12.00121
A32: 31 | B32: =Inventario_Activos!B5 -> Producción | C32: =Inventario_Activos!C5 -> Recursos Humanos | D32: =Inventario_Activos!D5 -> Administrador de sistemas | E32: Seguridad Física | F32: Sin control de acceso a áreas críticas para el administrador de sistemas | G32: Ingreso no autorizado a zonas restringidas | H32: 2 | I32: 3 | J32: =H32*I32 -> 6 | K32: =INDEX(Escalas!$F$2:$F$5,MATCH(J32,Escalas!$E$2:$E$5,1)) -> Moderado | L32: =INDEX(Inventario_Activos!$I$2:$I$16,MATCH(D32,Inventario_Activos!$D$2:$D$16,0)) -> 3 | M32: =ROUND(J32*L32/5,0) -> 4 | N32: =INDEX(Escalas!$F$2:$F$5,MATCH(M32,Escalas!$E$2:$E$5,1)) -> Bajo | O32: Reducir/Mitigar | P32: Control de acceso físico basado en roles y bitácora de ingreso. | Q32: =J32+(152-ROW())/100000 -> 6.0012
A33: 32 | B33: =Inventario_Activos!B5 -> Producción | C33: =Inventario_Activos!C5 -> Recursos Humanos | D33: =Inventario_Activos!D5 -> Administrador de sistemas | E33: Seguridad de Red | F33: Acceso remoto del administrador sin restricciones ni VPN | G33: Interceptación de sesiones de administración remota | H33: 3 | I33: 5 | J33: =H33*I33 -> 15 | K33: =INDEX(Escalas!$F$2:$F$5,MATCH(J33,Escalas!$E$2:$E$5,1)) -> Alto | L33: =INDEX(Inventario_Activos!$I$2:$I$16,MATCH(D33,Inventario_Activos!$D$2:$D$16,0)) -> 3 | M33: =ROUND(J33*L33/5,0) -> 9 | N33: =INDEX(Escalas!$F$2:$F$5,MATCH(M33,Escalas!$E$2:$E$5,1)) -> Moderado | O33: Reducir/Mitigar | P33: Acceso remoto únicamente mediante VPN con MFA. | Q33: =J33+(152-ROW())/100000 -> 15.00119
A34: 33 | B34: =Inventario_Activos!B5 -> Producción | C34: =Inventario_Activos!C5 -> Recursos Humanos | D34: =Inventario_Activos!D5 -> Administrador de sistemas | E34: Seguridad de Host | F34: Estación del administrador sin controles reforzados pese a sus privilegios | G34: Compromiso del equipo usado para tareas administrativas | H34: 3 | I34: 5 | J34: =H34*I34 -> 15 | K34: =INDEX(Escalas!$F$2:$F$5,MATCH(J34,Escalas!$E$2:$E$5,1)) -> Alto | L34: =INDEX(Inventario_Activos!$I$2:$I$16,MATCH(D34,Inventario_Activos!$D$2:$D$16,0)) -> 3 | M34: =ROUND(J34*L34/5,0) -> 9 | N34: =INDEX(Escalas!$F$2:$F$5,MATCH(M34,Escalas!$E$2:$E$5,1)) -> Moderado | O34: Reducir/Mitigar | P34: Estación dedicada y reforzada (PAW) para tareas administrativas. | Q34: =J34+(152-ROW())/100000 -> 15.00118
A35: 34 | B35: =Inventario_Activos!B5 -> Producción | C35: =Inventario_Activos!C5 -> Recursos Humanos | D35: =Inventario_Activos!D5 -> Administrador de sistemas | E35: Seguridad de Aplicación | F35: Uso de una sola cuenta de administrador para múltiples sistemas | G35: Movimiento lateral en caso de compromiso de la cuenta | H35: 3 | I35: 5 | J35: =H35*I35 -> 15 | K35: =INDEX(Escalas!$F$2:$F$5,MATCH(J35,Escalas!$E$2:$E$5,1)) -> Alto | L35: =INDEX(Inventario_Activos!$I$2:$I$16,MATCH(D35,Inventario_Activos!$D$2:$D$16,0)) -> 3 | M35: =ROUND(J35*L35/5,0) -> 9 | N35: =INDEX(Escalas!$F$2:$F$5,MATCH(M35,Escalas!$E$2:$E$5,1)) -> Moderado | O35: Reducir/Mitigar | P35: Cuentas administrativas separadas por sistema y uso de PAM. | Q35: =J35+(152-ROW())/100000 -> 15.00117
A36: 35 | B36: =Inventario_Activos!B5 -> Producción | C36: =Inventario_Activos!C5 -> Recursos Humanos | D36: =Inventario_Activos!D5 -> Administrador de sistemas | E36: Seguridad de Datos | F36: Acceso amplio del administrador a todos los datos sin justificación operativa | G36: Abuso de privilegios para acceder a información sensible | H36: 2 | I36: 4 | J36: =H36*I36 -> 8 | K36: =INDEX(Escalas!$F$2:$F$5,MATCH(J36,Escalas!$E$2:$E$5,1)) -> Moderado | L36: =INDEX(Inventario_Activos!$I$2:$I$16,MATCH(D36,Inventario_Activos!$D$2:$D$16,0)) -> 3 | M36: =ROUND(J36*L36/5,0) -> 5 | N36: =INDEX(Escalas!$F$2:$F$5,MATCH(M36,Escalas!$E$2:$E$5,1)) -> Bajo | O36: Reducir/Mitigar | P36: Limitar el acceso a datos según necesidad y registrar accesos privilegiados. | Q36: =J36+(152-ROW())/100000 -> 8.00116
A37: 36 | B37: =Inventario_Activos!B5 -> Producción | C37: =Inventario_Activos!C5 -> Recursos Humanos | D37: =Inventario_Activos!D5 -> Administrador de sistemas | E37: Gestión de Identidad y Acceso | F37: Falta de revisión periódica de privilegios asignados al rol | G37: Acumulación de privilegios innecesarios (privilege creep) | H37: 3 | I37: 4 | J37: =H37*I37 -> 12 | K37: =INDEX(Escalas!$F$2:$F$5,MATCH(J37,Escalas!$E$2:$E$5,1)) -> Alto | L37: =INDEX(Inventario_Activos!$I$2:$I$16,MATCH(D37,Inventario_Activos!$D$2:$D$16,0)) -> 3 | M37: =ROUND(J37*L37/5,0) -> 7 | N37: =INDEX(Escalas!$F$2:$F$5,MATCH(M37,Escalas!$E$2:$E$5,1)) -> Moderado | O37: Reducir/Mitigar | P37: Revisión periódica de privilegios y certificación de accesos. | Q37: =J37+(152-ROW())/100000 -> 12.00115
A38: 37 | B38: =Inventario_Activos!B5 -> Producción | C38: =Inventario_Activos!C5 -> Recursos Humanos | D38: =Inventario_Activos!D5 -> Administrador de sistemas | E38: Monitoreo y Respuesta | F38: Actividades del administrador no auditadas de forma independiente | G38: Acciones maliciosas o erróneas sin detección (amenaza interna) | H38: 3 | I38: 5 | J38: =H38*I38 -> 15 | K38: =INDEX(Escalas!$F$2:$F$5,MATCH(J38,Escalas!$E$2:$E$5,1)) -> Alto | L38: =INDEX(Inventario_Activos!$I$2:$I$16,MATCH(D38,Inventario_Activos!$D$2:$D$16,0)) -> 3 | M38: =ROUND(J38*L38/5,0) -> 9 | N38: =INDEX(Escalas!$F$2:$F$5,MATCH(M38,Escalas!$E$2:$E$5,1)) -> Moderado | O38: Reducir/Mitigar | P38: Auditoría independiente y grabación de sesiones privilegiadas. | Q38: =J38+(152-ROW())/100000 -> 15.00114
A39: 38 | B39: =Inventario_Activos!B5 -> Producción | C39: =Inventario_Activos!C5 -> Recursos Humanos | D39: =Inventario_Activos!D5 -> Administrador de sistemas | E39: Continuidad y Respaldo | F39: Dependencia de una sola persona para tareas administrativas críticas | G39: Interrupción de operaciones ante ausencia del administrador | H39: 3 | I39: 4 | J39: =H39*I39 -> 12 | K39: =INDEX(Escalas!$F$2:$F$5,MATCH(J39,Escalas!$E$2:$E$5,1)) -> Alto | L39: =INDEX(Inventario_Activos!$I$2:$I$16,MATCH(D39,Inventario_Activos!$D$2:$D$16,0)) -> 3 | M39: =ROUND(J39*L39/5,0) -> 7 | N39: =INDEX(Escalas!$F$2:$F$5,MATCH(M39,Escalas!$E$2:$E$5,1)) -> Moderado | O39: Reducir/Mitigar | P39: Documentar procedimientos y contar con un administrador de respaldo. | Q39: =J39+(152-ROW())/100000 -> 12.00113
A40: 39 | B40: =Inventario_Activos!B5 -> Producción | C40: =Inventario_Activos!C5 -> Recursos Humanos | D40: =Inventario_Activos!D5 -> Administrador de sistemas | E40: Seguridad Perimetral | F40: Acceso administrativo posible desde cualquier ubicación sin restricción geográfica | G40: Acceso indebido desde ubicaciones no habituales | H40: 2 | I40: 4 | J40: =H40*I40 -> 8 | K40: =INDEX(Escalas!$F$2:$F$5,MATCH(J40,Escalas!$E$2:$E$5,1)) -> Moderado | L40: =INDEX(Inventario_Activos!$I$2:$I$16,MATCH(D40,Inventario_Activos!$D$2:$D$16,0)) -> 3 | M40: =ROUND(J40*L40/5,0) -> 5 | N40: =INDEX(Escalas!$F$2:$F$5,MATCH(M40,Escalas!$E$2:$E$5,1)) -> Bajo | O40: Reducir/Mitigar | P40: Restringir accesos administrativos por geolocalización/IP y alertar anomalías. | Q40: =J40+(152-ROW())/100000 -> 8.00112
A41: 40 | B41: =Inventario_Activos!B5 -> Producción | C41: =Inventario_Activos!C5 -> Recursos Humanos | D41: =Inventario_Activos!D5 -> Administrador de sistemas | E41: Concientización y Procesos | F41: Falta de capacitación continua en nuevas amenazas de ciberseguridad | G41: Desactualización frente a nuevas técnicas de ataque (ingeniería social) | H41: 3 | I41: 4 | J41: =H41*I41 -> 12 | K41: =INDEX(Escalas!$F$2:$F$5,MATCH(J41,Escalas!$E$2:$E$5,1)) -> Alto | L41: =INDEX(Inventario_Activos!$I$2:$I$16,MATCH(D41,Inventario_Activos!$D$2:$D$16,0)) -> 3 | M41: =ROUND(J41*L41/5,0) -> 7 | N41: =INDEX(Escalas!$F$2:$F$5,MATCH(M41,Escalas!$E$2:$E$5,1)) -> Moderado | O41: Reducir/Mitigar | P41: Capacitación continua y simulacros de phishing dirigidos. | Q41: =J41+(152-ROW())/100000 -> 12.00111
A42: 41 | B42: =Inventario_Activos!B6 -> Producción | C42: =Inventario_Activos!C6 -> Hardware | D42: =Inventario_Activos!D6 -> Firewall / Router de borde | E42: Seguridad Física | F42: Firewall/router ubicado en gabinete sin cerradura | G42: Manipulación física del dispositivo perimetral | H42: 2 | I42: 4 | J42: =H42*I42 -> 8 | K42: =INDEX(Escalas!$F$2:$F$5,MATCH(J42,Escalas!$E$2:$E$5,1)) -> Moderado | L42: =INDEX(Inventario_Activos!$I$2:$I$16,MATCH(D42,Inventario_Activos!$D$2:$D$16,0)) -> 3 | M42: =ROUND(J42*L42/5,0) -> 5 | N42: =INDEX(Escalas!$F$2:$F$5,MATCH(M42,Escalas!$E$2:$E$5,1)) -> Bajo | O42: Reducir/Mitigar | P42: Reubicar el equipo en rack con cerradura y control de acceso. | Q42: =J42+(152-ROW())/100000 -> 8.0011
A43: 42 | B43: =Inventario_Activos!B6 -> Producción | C43: =Inventario_Activos!C6 -> Hardware | D43: =Inventario_Activos!D6 -> Firewall / Router de borde | E43: Seguridad de Red | F43: Interfaz de administración accesible desde la red interna sin restricción | G43: Reconfiguración no autorizada de reglas | H43: 3 | I43: 5 | J43: =H43*I43 -> 15 | K43: =INDEX(Escalas!$F$2:$F$5,MATCH(J43,Escalas!$E$2:$E$5,1)) -> Alto | L43: =INDEX(Inventario_Activos!$I$2:$I$16,MATCH(D43,Inventario_Activos!$D$2:$D$16,0)) -> 3 | M43: =ROUND(J43*L43/5,0) -> 9 | N43: =INDEX(Escalas!$F$2:$F$5,MATCH(M43,Escalas!$E$2:$E$5,1)) -> Moderado | O43: Reducir/Mitigar | P43: Aislar la interfaz de gestión en una VLAN de administración dedicada. | Q43: =J43+(152-ROW())/100000 -> 15.00109
A44: 43 | B44: =Inventario_Activos!B6 -> Producción | C44: =Inventario_Activos!C6 -> Hardware | D44: =Inventario_Activos!D6 -> Firewall / Router de borde | E44: Seguridad de Host | F44: Firmware del firewall desactualizado | G44: Explotación de vulnerabilidades conocidas del firmware | H44: 3 | I44: 5 | J44: =H44*I44 -> 15 | K44: =INDEX(Escalas!$F$2:$F$5,MATCH(J44,Escalas!$E$2:$E$5,1)) -> Alto | L44: =INDEX(Inventario_Activos!$I$2:$I$16,MATCH(D44,Inventario_Activos!$D$2:$D$16,0)) -> 3 | M44: =ROUND(J44*L44/5,0) -> 9 | N44: =INDEX(Escalas!$F$2:$F$5,MATCH(M44,Escalas!$E$2:$E$5,1)) -> Moderado | O44: Reducir/Mitigar | P44: Plan de actualización de firmware y suscripción a boletines del fabricante. | Q44: =J44+(152-ROW())/100000 -> 15.00108
A45: 44 | B45: =Inventario_Activos!B6 -> Producción | C45: =Inventario_Activos!C6 -> Hardware | D45: =Inventario_Activos!D6 -> Firewall / Router de borde | E45: Seguridad de Aplicación | F45: Panel de administración web sin límite de intentos de login | G45: Ataque de fuerza bruta a la consola | H45: 3 | I45: 4 | J45: =H45*I45 -> 12 | K45: =INDEX(Escalas!$F$2:$F$5,MATCH(J45,Escalas!$E$2:$E$5,1)) -> Alto | L45: =INDEX(Inventario_Activos!$I$2:$I$16,MATCH(D45,Inventario_Activos!$D$2:$D$16,0)) -> 3 | M45: =ROUND(J45*L45/5,0) -> 7 | N45: =INDEX(Escalas!$F$2:$F$5,MATCH(M45,Escalas!$E$2:$E$5,1)) -> Moderado | O45: Reducir/Mitigar | P45: Bloqueo por intentos fallidos y autenticación multifactor. | Q45: =J45+(152-ROW())/100000 -> 12.00107
A46: 45 | B46: =Inventario_Activos!B6 -> Producción | C46: =Inventario_Activos!C6 -> Hardware | D46: =Inventario_Activos!D6 -> Firewall / Router de borde | E46: Seguridad de Datos | F46: Configuración del firewall sin respaldo cifrado | G46: Exposición de reglas de seguridad ante robo de respaldo | H46: 2 | I46: 3 | J46: =H46*I46 -> 6 | K46: =INDEX(Escalas!$F$2:$F$5,MATCH(J46,Escalas!$E$2:$E$5,1)) -> Moderado | L46: =INDEX(Inventario_Activos!$I$2:$I$16,MATCH(D46,Inventario_Activos!$D$2:$D$16,0)) -> 3 | M46: =ROUND(J46*L46/5,0) -> 4 | N46: =INDEX(Escalas!$F$2:$F$5,MATCH(M46,Escalas!$E$2:$E$5,1)) -> Bajo | O46: Reducir/Mitigar | P46: Cifrar y resguardar los respaldos de configuración. | Q46: =J46+(152-ROW())/100000 -> 6.00106
A47: 46 | B47: =Inventario_Activos!B6 -> Producción | C47: =Inventario_Activos!C6 -> Hardware | D47: =Inventario_Activos!D6 -> Firewall / Router de borde | E47: Gestión de Identidad y Acceso | F47: Cuenta única de administrador para todo el equipo de redes | G47: Falta de trazabilidad en cambios de configuración | H47: 3 | I47: 4 | J47: =H47*I47 -> 12 | K47: =INDEX(Escalas!$F$2:$F$5,MATCH(J47,Escalas!$E$2:$E$5,1)) -> Alto | L47: =INDEX(Inventario_Activos!$I$2:$I$16,MATCH(D47,Inventario_Activos!$D$2:$D$16,0)) -> 3 | M47: =ROUND(J47*L47/5,0) -> 7 | N47: =INDEX(Escalas!$F$2:$F$5,MATCH(M47,Escalas!$E$2:$E$5,1)) -> Moderado | O47: Reducir/Mitigar | P47: Cuentas individuales con roles y registro de auditoría (AAA/RADIUS). | Q47: =J47+(152-ROW())/100000 -> 12.00105
A48: 47 | B48: =Inventario_Activos!B6 -> Producción | C48: =Inventario_Activos!C6 -> Hardware | D48: =Inventario_Activos!D6 -> Firewall / Router de borde | E48: Monitoreo y Respuesta | F48: No se revisan los logs del firewall regularmente | G48: Intentos de intrusión no detectados | H48: 3 | I48: 4 | J48: =H48*I48 -> 12 | K48: =INDEX(Escalas!$F$2:$F$5,MATCH(J48,Escalas!$E$2:$E$5,1)) -> Alto | L48: =INDEX(Inventario_Activos!$I$2:$I$16,MATCH(D48,Inventario_Activos!$D$2:$D$16,0)) -> 3 | M48: =ROUND(J48*L48/5,0) -> 7 | N48: =INDEX(Escalas!$F$2:$F$5,MATCH(M48,Escalas!$E$2:$E$5,1)) -> Moderado | O48: Reducir/Mitigar | P48: Envío de logs a SIEM con alertas de eventos críticos. | Q48: =J48+(152-ROW())/100000 -> 12.00104
A49: 48 | B49: =Inventario_Activos!B6 -> Producción | C49: =Inventario_Activos!C6 -> Hardware | D49: =Inventario_Activos!D6 -> Firewall / Router de borde | E49: Continuidad y Respaldo | F49: No existe equipo de respaldo (failover) para el firewall | G49: Interrupción total de conectividad ante falla | H49: 2 | I49: 5 | J49: =H49*I49 -> 10 | K49: =INDEX(Escalas!$F$2:$F$5,MATCH(J49,Escalas!$E$2:$E$5,1)) -> Moderado | L49: =INDEX(Inventario_Activos!$I$2:$I$16,MATCH(D49,Inventario_Activos!$D$2:$D$16,0)) -> 3 | M49: =ROUND(J49*L49/5,0) -> 6 | N49: =INDEX(Escalas!$F$2:$F$5,MATCH(M49,Escalas!$E$2:$E$5,1)) -> Moderado | O49: Reducir/Mitigar | P49: Implementar configuración de alta disponibilidad (HA) activo-pasivo. | Q49: =J49+(152-ROW())/100000 -> 10.00103
A50: 49 | B50: =Inventario_Activos!B6 -> Producción | C50: =Inventario_Activos!C6 -> Hardware | D50: =Inventario_Activos!D6 -> Firewall / Router de borde | E50: Seguridad Perimetral | F50: Reglas de firewall permisivas (ANY-ANY) heredadas | G50: Tráfico malicioso permitido hacia la red interna | H50: 3 | I50: 5 | J50: =H50*I50 -> 15 | K50: =INDEX(Escalas!$F$2:$F$5,MATCH(J50,Escalas!$E$2:$E$5,1)) -> Alto | L50: =INDEX(Inventario_Activos!$I$2:$I$16,MATCH(D50,Inventario_Activos!$D$2:$D$16,0)) -> 3 | M50: =ROUND(J50*L50/5,0) -> 9 | N50: =INDEX(Escalas!$F$2:$F$5,MATCH(M50,Escalas!$E$2:$E$5,1)) -> Moderado | O50: Reducir/Mitigar | P50: Auditoría y depuración de reglas siguiendo el principio de mínimo privilegio. | Q50: =J50+(152-ROW())/100000 -> 15.00102
A51: 50 | B51: =Inventario_Activos!B6 -> Producción | C51: =Inventario_Activos!C6 -> Hardware | D51: =Inventario_Activos!D6 -> Firewall / Router de borde | E51: Concientización y Procesos | F51: Falta de procedimiento documentado de cambios | G51: Cambios no controlados que generan brechas | H51: 2 | I51: 3 | J51: =H51*I51 -> 6 | K51: =INDEX(Escalas!$F$2:$F$5,MATCH(J51,Escalas!$E$2:$E$5,1)) -> Moderado | L51: =INDEX(Inventario_Activos!$I$2:$I$16,MATCH(D51,Inventario_Activos!$D$2:$D$16,0)) -> 3 | M51: =ROUND(J51*L51/5,0) -> 4 | N51: =INDEX(Escalas!$F$2:$F$5,MATCH(M51,Escalas!$E$2:$E$5,1)) -> Bajo | O51: Reducir/Mitigar | P51: Implementar proceso formal de gestión de cambios (change management). | Q51: =J51+(152-ROW())/100000 -> 6.00101
A52: 51 | B52: =Inventario_Activos!B7 -> Pruebas | C52: =Inventario_Activos!C7 -> Hardware | D52: =Inventario_Activos!D7 -> Servidor de pruebas | E52: Seguridad Física | F52: Servidor de pruebas ubicado en área de oficina sin control de acceso | G52: Acceso físico no autorizado | H52: 2 | I52: 2 | J52: =H52*I52 -> 4 | K52: =INDEX(Escalas!$F$2:$F$5,MATCH(J52,Escalas!$E$2:$E$5,1)) -> Bajo | L52: =INDEX(Inventario_Activos!$I$2:$I$16,MATCH(D52,Inventario_Activos!$D$2:$D$16,0)) -> 3 | M52: =ROUND(J52*L52/5,0) -> 2 | N52: =INDEX(Escalas!$F$2:$F$5,MATCH(M52,Escalas!$E$2:$E$5,1)) -> Bajo | O52: Aceptar | P52: Aceptar el riesgo por bajo impacto, documentando la decisión, o reubicar a rack cerrado. | Q52: =J52+(152-ROW())/100000 -> 4.001
A53: 52 | B53: =Inventario_Activos!B7 -> Pruebas | C53: =Inventario_Activos!C7 -> Hardware | D53: =Inventario_Activos!D7 -> Servidor de pruebas | E53: Seguridad de Red | F53: Servidor de pruebas conectado a la misma red que producción | G53: Pivote hacia sistemas productivos | H53: 3 | I53: 4 | J53: =H53*I53 -> 12 | K53: =INDEX(Escalas!$F$2:$F$5,MATCH(J53,Escalas!$E$2:$E$5,1)) -> Alto | L53: =INDEX(Inventario_Activos!$I$2:$I$16,MATCH(D53,Inventario_Activos!$D$2:$D$16,0)) -> 3 | M53: =ROUND(J53*L53/5,0) -> 7 | N53: =INDEX(Escalas!$F$2:$F$5,MATCH(M53,Escalas!$E$2:$E$5,1)) -> Moderado | O53: Reducir/Mitigar | P53: Segmentar la red de pruebas en una VLAN aislada de producción. | Q53: =J53+(152-ROW())/100000 -> 12.00099
A54: 53 | B54: =Inventario_Activos!B7 -> Pruebas | C54: =Inventario_Activos!C7 -> Hardware | D54: =Inventario_Activos!D7 -> Servidor de pruebas | E54: Seguridad de Host | F54: Sistema operativo de pruebas sin parches por priorizarse funcionalidad | G54: Explotación de vulnerabilidades sin corregir | H54: 3 | I54: 3 | J54: =H54*I54 -> 9 | K54: =INDEX(Escalas!$F$2:$F$5,MATCH(J54,Escalas!$E$2:$E$5,1)) -> Moderado | L54: =INDEX(Inventario_Activos!$I$2:$I$16,MATCH(D54,Inventario_Activos!$D$2:$D$16,0)) -> 3 | M54: =ROUND(J54*L54/5,0) -> 5 | N54: =INDEX(Escalas!$F$2:$F$5,MATCH(M54,Escalas!$E$2:$E$5,1)) -> Bajo | O54: Reducir/Mitigar | P54: Incluir el servidor de pruebas en el ciclo de gestión de parches. | Q54: =J54+(152-ROW())/100000 -> 9.00098
A55: 54 | B55: =Inventario_Activos!B7 -> Pruebas | C55: =Inventario_Activos!C7 -> Hardware | D55: =Inventario_Activos!D7 -> Servidor de pruebas | E55: Seguridad de Aplicación | F55: Aplicaciones en prueba con configuraciones de depuración activas | G55: Exposición de información sensible por mensajes de error | H55: 3 | I55: 3 | J55: =H55*I55 -> 9 | K55: =INDEX(Escalas!$F$2:$F$5,MATCH(J55,Escalas!$E$2:$E$5,1)) -> Moderado | L55: =INDEX(Inventario_Activos!$I$2:$I$16,MATCH(D55,Inventario_Activos!$D$2:$D$16,0)) -> 3 | M55: =ROUND(J55*L55/5,0) -> 5 | N55: =INDEX(Escalas!$F$2:$F$5,MATCH(M55,Escalas!$E$2:$E$5,1)) -> Bajo | O55: Reducir/Mitigar | P55: Deshabilitar el modo debug antes de exponer el ambiente. | Q55: =J55+(152-ROW())/100000 -> 9.00097
A56: 55 | B56: =Inventario_Activos!B7 -> Pruebas | C56: =Inventario_Activos!C7 -> Hardware | D56: =Inventario_Activos!D7 -> Servidor de pruebas | E56: Seguridad de Datos | F56: Uso de datos reales de producción sin anonimizar | G56: Fuga de información confidencial desde el ambiente de pruebas | H56: 3 | I56: 4 | J56: =H56*I56 -> 12 | K56: =INDEX(Escalas!$F$2:$F$5,MATCH(J56,Escalas!$E$2:$E$5,1)) -> Alto | L56: =INDEX(Inventario_Activos!$I$2:$I$16,MATCH(D56,Inventario_Activos!$D$2:$D$16,0)) -> 3 | M56: =ROUND(J56*L56/5,0) -> 7 | N56: =INDEX(Escalas!$F$2:$F$5,MATCH(M56,Escalas!$E$2:$E$5,1)) -> Moderado | O56: Reducir/Mitigar | P56: Anonimizar/enmascarar datos antes de cargarlos en pruebas. | Q56: =J56+(152-ROW())/100000 -> 12.00096
A57: 56 | B57: =Inventario_Activos!B7 -> Pruebas | C57: =Inventario_Activos!C7 -> Hardware | D57: =Inventario_Activos!D7 -> Servidor de pruebas | E57: Gestión de Identidad y Acceso | F57: Credenciales por defecto sin cambiar en el ambiente de pruebas | G57: Acceso no autorizado al servidor | H57: 3 | I57: 3 | J57: =H57*I57 -> 9 | K57: =INDEX(Escalas!$F$2:$F$5,MATCH(J57,Escalas!$E$2:$E$5,1)) -> Moderado | L57: =INDEX(Inventario_Activos!$I$2:$I$16,MATCH(D57,Inventario_Activos!$D$2:$D$16,0)) -> 3 | M57: =ROUND(J57*L57/5,0) -> 5 | N57: =INDEX(Escalas!$F$2:$F$5,MATCH(M57,Escalas!$E$2:$E$5,1)) -> Bajo | O57: Reducir/Mitigar | P57: Forzar cambio de credenciales por defecto y política de contraseñas. | Q57: =J57+(152-ROW())/100000 -> 9.00095
A58: 57 | B58: =Inventario_Activos!B7 -> Pruebas | C58: =Inventario_Activos!C7 -> Hardware | D58: =Inventario_Activos!D7 -> Servidor de pruebas | E58: Monitoreo y Respuesta | F58: Sin monitoreo activo por considerarse ambiente no crítico | G58: Uso indebido no detectado | H58: 3 | I58: 2 | J58: =H58*I58 -> 6 | K58: =INDEX(Escalas!$F$2:$F$5,MATCH(J58,Escalas!$E$2:$E$5,1)) -> Moderado | L58: =INDEX(Inventario_Activos!$I$2:$I$16,MATCH(D58,Inventario_Activos!$D$2:$D$16,0)) -> 3 | M58: =ROUND(J58*L58/5,0) -> 4 | N58: =INDEX(Escalas!$F$2:$F$5,MATCH(M58,Escalas!$E$2:$E$5,1)) -> Bajo | O58: Reducir/Mitigar | P58: Incluir el servidor en el monitoreo básico centralizado. | Q58: =J58+(152-ROW())/100000 -> 6.00094
A59: 58 | B59: =Inventario_Activos!B7 -> Pruebas | C59: =Inventario_Activos!C7 -> Hardware | D59: =Inventario_Activos!D7 -> Servidor de pruebas | E59: Continuidad y Respaldo | F59: Sin respaldo del ambiente de pruebas | G59: Pérdida de configuraciones y avances de prueba | H59: 2 | I59: 2 | J59: =H59*I59 -> 4 | K59: =INDEX(Escalas!$F$2:$F$5,MATCH(J59,Escalas!$E$2:$E$5,1)) -> Bajo | L59: =INDEX(Inventario_Activos!$I$2:$I$16,MATCH(D59,Inventario_Activos!$D$2:$D$16,0)) -> 3 | M59: =ROUND(J59*L59/5,0) -> 2 | N59: =INDEX(Escalas!$F$2:$F$5,MATCH(M59,Escalas!$E$2:$E$5,1)) -> Bajo | O59: Aceptar | P59: Aceptar el riesgo o programar respaldos de baja frecuencia. | Q59: =J59+(152-ROW())/100000 -> 4.00093
A60: 59 | B60: =Inventario_Activos!B7 -> Pruebas | C60: =Inventario_Activos!C7 -> Hardware | D60: =Inventario_Activos!D7 -> Servidor de pruebas | E60: Seguridad Perimetral | F60: Acceso remoto (RDP/SSH) expuesto directamente a internet | G60: Ataques de fuerza bruta desde internet | H60: 4 | I60: 4 | J60: =H60*I60 -> 16 | K60: =INDEX(Escalas!$F$2:$F$5,MATCH(J60,Escalas!$E$2:$E$5,1)) -> Alto | L60: =INDEX(Inventario_Activos!$I$2:$I$16,MATCH(D60,Inventario_Activos!$D$2:$D$16,0)) -> 3 | M60: =ROUND(J60*L60/5,0) -> 10 | N60: =INDEX(Escalas!$F$2:$F$5,MATCH(M60,Escalas!$E$2:$E$5,1)) -> Moderado | O60: Reducir/Mitigar | P60: Cerrar el acceso directo a internet y usar VPN o bastion host. | Q60: =J60+(152-ROW())/100000 -> 16.00092
A61: 60 | B61: =Inventario_Activos!B7 -> Pruebas | C61: =Inventario_Activos!C7 -> Hardware | D61: =Inventario_Activos!D7 -> Servidor de pruebas | E61: Concientización y Procesos | F61: Falta de lineamientos sobre uso de datos en ambientes de prueba | G61: Manejo inadecuado de información sensible por el equipo de QA | H61: 3 | I61: 3 | J61: =H61*I61 -> 9 | K61: =INDEX(Escalas!$F$2:$F$5,MATCH(J61,Escalas!$E$2:$E$5,1)) -> Moderado | L61: =INDEX(Inventario_Activos!$I$2:$I$16,MATCH(D61,Inventario_Activos!$D$2:$D$16,0)) -> 3 | M61: =ROUND(J61*L61/5,0) -> 5 | N61: =INDEX(Escalas!$F$2:$F$5,MATCH(M61,Escalas!$E$2:$E$5,1)) -> Bajo | O61: Reducir/Mitigar | P61: Política de manejo de datos de prueba y capacitación al equipo. | Q61: =J61+(152-ROW())/100000 -> 9.00091
A62: 61 | B62: =Inventario_Activos!B8 -> Pruebas | C62: =Inventario_Activos!C8 -> Software | D62: =Inventario_Activos!D8 -> Ambiente de staging web | E62: Seguridad Física | F62: Servidor de staging alojado en el mismo rack sin separación lógica | G62: Acceso físico no controlado | H62: 2 | I62: 2 | J62: =H62*I62 -> 4 | K62: =INDEX(Escalas!$F$2:$F$5,MATCH(J62,Escalas!$E$2:$E$5,1)) -> Bajo | L62: =INDEX(Inventario_Activos!$I$2:$I$16,MATCH(D62,Inventario_Activos!$D$2:$D$16,0)) -> 3 | M62: =ROUND(J62*L62/5,0) -> 2 | N62: =INDEX(Escalas!$F$2:$F$5,MATCH(M62,Escalas!$E$2:$E$5,1)) -> Bajo | O62: Aceptar | P62: Aceptar el riesgo o segregar físicamente el equipo del resto de la infraestructura. | Q62: =J62+(152-ROW())/100000 -> 4.0009
A63: 62 | B63: =Inventario_Activos!B8 -> Pruebas | C63: =Inventario_Activos!C8 -> Software | D63: =Inventario_Activos!D8 -> Ambiente de staging web | E63: Seguridad de Red | F63: Staging accesible desde internet sin restricción de IP | G63: Escaneo y explotación por actores externos | H63: 3 | I63: 4 | J63: =H63*I63 -> 12 | K63: =INDEX(Escalas!$F$2:$F$5,MATCH(J63,Escalas!$E$2:$E$5,1)) -> Alto | L63: =INDEX(Inventario_Activos!$I$2:$I$16,MATCH(D63,Inventario_Activos!$D$2:$D$16,0)) -> 3 | M63: =ROUND(J63*L63/5,0) -> 7 | N63: =INDEX(Escalas!$F$2:$F$5,MATCH(M63,Escalas!$E$2:$E$5,1)) -> Moderado | O63: Reducir/Mitigar | P63: Restringir acceso a IPs autorizadas y usar autenticación básica adicional. | Q63: =J63+(152-ROW())/100000 -> 12.00089
A64: 63 | B64: =Inventario_Activos!B8 -> Pruebas | C64: =Inventario_Activos!C8 -> Software | D64: =Inventario_Activos!D8 -> Ambiente de staging web | E64: Seguridad de Host | F64: Servidor de staging con configuración idéntica a producción pero sin parches recientes | G64: Explotación de vulnerabilidades | H64: 3 | I64: 3 | J64: =H64*I64 -> 9 | K64: =INDEX(Escalas!$F$2:$F$5,MATCH(J64,Escalas!$E$2:$E$5,1)) -> Moderado | L64: =INDEX(Inventario_Activos!$I$2:$I$16,MATCH(D64,Inventario_Activos!$D$2:$D$16,0)) -> 3 | M64: =ROUND(J64*L64/5,0) -> 5 | N64: =INDEX(Escalas!$F$2:$F$5,MATCH(M64,Escalas!$E$2:$E$5,1)) -> Bajo | O64: Reducir/Mitigar | P64: Incluir staging en el ciclo de parcheo regular. | Q64: =J64+(152-ROW())/100000 -> 9.00088
A65: 64 | B65: =Inventario_Activos!B8 -> Pruebas | C65: =Inventario_Activos!C8 -> Software | D65: =Inventario_Activos!D8 -> Ambiente de staging web | E65: Seguridad de Aplicación | F65: Código en staging con features no probadas y mensajes de error detallados | G65: Divulgación de información técnica (stack traces) | H65: 3 | I65: 3 | J65: =H65*I65 -> 9 | K65: =INDEX(Escalas!$F$2:$F$5,MATCH(J65,Escalas!$E$2:$E$5,1)) -> Moderado | L65: =INDEX(Inventario_Activos!$I$2:$I$16,MATCH(D65,Inventario_Activos!$D$2:$D$16,0)) -> 3 | M65: =ROUND(J65*L65/5,0) -> 5 | N65: =INDEX(Escalas!$F$2:$F$5,MATCH(M65,Escalas!$E$2:$E$5,1)) -> Bajo | O65: Reducir/Mitigar | P65: Configurar manejo de errores genérico también en staging. | Q65: =J65+(152-ROW())/100000 -> 9.00087
A66: 65 | B66: =Inventario_Activos!B8 -> Pruebas | C66: =Inventario_Activos!C8 -> Software | D66: =Inventario_Activos!D8 -> Ambiente de staging web | E66: Seguridad de Datos | F66: Uso de copia de base de datos de producción sin anonimizar | G66: Exposición de datos reales de clientes | H66: 3 | I66: 5 | J66: =H66*I66 -> 15 | K66: =INDEX(Escalas!$F$2:$F$5,MATCH(J66,Escalas!$E$2:$E$5,1)) -> Alto | L66: =INDEX(Inventario_Activos!$I$2:$I$16,MATCH(D66,Inventario_Activos!$D$2:$D$16,0)) -> 3 | M66: =ROUND(J66*L66/5,0) -> 9 | N66: =INDEX(Escalas!$F$2:$F$5,MATCH(M66,Escalas!$E$2:$E$5,1)) -> Moderado | O66: Reducir/Mitigar | P66: Anonimización obligatoria de datos antes de cargarlos a staging. | Q66: =J66+(152-ROW())/100000 -> 15.00086
A67: 66 | B67: =Inventario_Activos!B8 -> Pruebas | C67: =Inventario_Activos!C8 -> Software | D67: =Inventario_Activos!D8 -> Ambiente de staging web | E67: Gestión de Identidad y Acceso | F67: Usuario y contraseña compartidos entre todo el equipo de QA | G67: Falta de trazabilidad de cambios | H67: 3 | I67: 3 | J67: =H67*I67 -> 9 | K67: =INDEX(Escalas!$F$2:$F$5,MATCH(J67,Escalas!$E$2:$E$5,1)) -> Moderado | L67: =INDEX(Inventario_Activos!$I$2:$I$16,MATCH(D67,Inventario_Activos!$D$2:$D$16,0)) -> 3 | M67: =ROUND(J67*L67/5,0) -> 5 | N67: =INDEX(Escalas!$F$2:$F$5,MATCH(M67,Escalas!$E$2:$E$5,1)) -> Bajo | O67: Reducir/Mitigar | P67: Cuentas individuales con inicio de sesión único (SSO) corporativo. | Q67: =J67+(152-ROW())/100000 -> 9.00085
A68: 67 | B68: =Inventario_Activos!B8 -> Pruebas | C68: =Inventario_Activos!C8 -> Software | D68: =Inventario_Activos!D8 -> Ambiente de staging web | E68: Monitoreo y Respuesta | F68: No se revisan logs del ambiente de staging | G68: Actividad anómala no detectada antes de pasar a producción | H68: 3 | I68: 3 | J68: =H68*I68 -> 9 | K68: =INDEX(Escalas!$F$2:$F$5,MATCH(J68,Escalas!$E$2:$E$5,1)) -> Moderado | L68: =INDEX(Inventario_Activos!$I$2:$I$16,MATCH(D68,Inventario_Activos!$D$2:$D$16,0)) -> 3 | M68: =ROUND(J68*L68/5,0) -> 5 | N68: =INDEX(Escalas!$F$2:$F$5,MATCH(M68,Escalas!$E$2:$E$5,1)) -> Bajo | O68: Reducir/Mitigar | P68: Integrar staging al monitoreo centralizado con alertas básicas. | Q68: =J68+(152-ROW())/100000 -> 9.00084
A69: 68 | B69: =Inventario_Activos!B8 -> Pruebas | C69: =Inventario_Activos!C8 -> Software | D69: =Inventario_Activos!D8 -> Ambiente de staging web | E69: Continuidad y Respaldo | F69: Sin respaldo del ambiente de staging | G69: Pérdida de configuración de pruebas | H69: 2 | I69: 2 | J69: =H69*I69 -> 4 | K69: =INDEX(Escalas!$F$2:$F$5,MATCH(J69,Escalas!$E$2:$E$5,1)) -> Bajo | L69: =INDEX(Inventario_Activos!$I$2:$I$16,MATCH(D69,Inventario_Activos!$D$2:$D$16,0)) -> 3 | M69: =ROUND(J69*L69/5,0) -> 2 | N69: =INDEX(Escalas!$F$2:$F$5,MATCH(M69,Escalas!$E$2:$E$5,1)) -> Bajo | O69: Aceptar | P69: Aceptar el riesgo dado el bajo impacto del ambiente. | Q69: =J69+(152-ROW())/100000 -> 4.00083
A70: 69 | B70: =Inventario_Activos!B8 -> Pruebas | C70: =Inventario_Activos!C8 -> Software | D70: =Inventario_Activos!D8 -> Ambiente de staging web | E70: Seguridad Perimetral | F70: Puertos de depuración (debug) abiertos al exterior | G70: Explotación de endpoints de desarrollo expuestos | H70: 3 | I70: 4 | J70: =H70*I70 -> 12 | K70: =INDEX(Escalas!$F$2:$F$5,MATCH(J70,Escalas!$E$2:$E$5,1)) -> Alto | L70: =INDEX(Inventario_Activos!$I$2:$I$16,MATCH(D70,Inventario_Activos!$D$2:$D$16,0)) -> 3 | M70: =ROUND(J70*L70/5,0) -> 7 | N70: =INDEX(Escalas!$F$2:$F$5,MATCH(M70,Escalas!$E$2:$E$5,1)) -> Moderado | O70: Reducir/Mitigar | P70: Cerrar puertos de depuración antes de publicar el ambiente. | Q70: =J70+(152-ROW())/100000 -> 12.00082
A71: 70 | B71: =Inventario_Activos!B8 -> Pruebas | C71: =Inventario_Activos!C8 -> Software | D71: =Inventario_Activos!D8 -> Ambiente de staging web | E71: Concientización y Procesos | F71: Falta de checklist de seguridad previo a promover cambios a producción | G71: Vulnerabilidades no detectadas que pasan a producción | H71: 3 | I71: 4 | J71: =H71*I71 -> 12 | K71: =INDEX(Escalas!$F$2:$F$5,MATCH(J71,Escalas!$E$2:$E$5,1)) -> Alto | L71: =INDEX(Inventario_Activos!$I$2:$I$16,MATCH(D71,Inventario_Activos!$D$2:$D$16,0)) -> 3 | M71: =ROUND(J71*L71/5,0) -> 7 | N71: =INDEX(Escalas!$F$2:$F$5,MATCH(M71,Escalas!$E$2:$E$5,1)) -> Moderado | O71: Reducir/Mitigar | P71: Checklist de seguridad y revisión de código previo al despliegue. | Q71: =J71+(152-ROW())/100000 -> 12.00081
A72: 71 | B72: =Inventario_Activos!B9 -> Pruebas | C72: =Inventario_Activos!C9 -> Datos | D72: =Inventario_Activos!D9 -> Datos de prueba anonimizados | E72: Seguridad Física | F72: Medios con datos de prueba sin resguardo físico | G72: Acceso físico no autorizado a medios de almacenamiento | H72: 2 | I72: 2 | J72: =H72*I72 -> 4 | K72: =INDEX(Escalas!$F$2:$F$5,MATCH(J72,Escalas!$E$2:$E$5,1)) -> Bajo | L72: =INDEX(Inventario_Activos!$I$2:$I$16,MATCH(D72,Inventario_Activos!$D$2:$D$16,0)) -> 3 | M72: =ROUND(J72*L72/5,0) -> 2 | N72: =INDEX(Escalas!$F$2:$F$5,MATCH(M72,Escalas!$E$2:$E$5,1)) -> Bajo | O72: Aceptar | P72: Aceptar el riesgo por bajo impacto, dado que los datos están anonimizados. | Q72: =J72+(152-ROW())/100000 -> 4.0008
A73: 72 | B73: =Inventario_Activos!B9 -> Pruebas | C73: =Inventario_Activos!C9 -> Datos | D73: =Inventario_Activos!D9 -> Datos de prueba anonimizados | E73: Seguridad de Red | F73: Transferencia de datos de prueba sin cifrado entre ambientes | G73: Intercepción de datos durante la carga a pruebas | H73: 2 | I73: 3 | J73: =H73*I73 -> 6 | K73: =INDEX(Escalas!$F$2:$F$5,MATCH(J73,Escalas!$E$2:$E$5,1)) -> Moderado | L73: =INDEX(Inventario_Activos!$I$2:$I$16,MATCH(D73,Inventario_Activos!$D$2:$D$16,0)) -> 3 | M73: =ROUND(J73*L73/5,0) -> 4 | N73: =INDEX(Escalas!$F$2:$F$5,MATCH(M73,Escalas!$E$2:$E$5,1)) -> Bajo | O73: Reducir/Mitigar | P73: Cifrar la transferencia de datos entre ambientes (SFTP/TLS). | Q73: =J73+(152-ROW())/100000 -> 6.00079
A74: 73 | B74: =Inventario_Activos!B9 -> Pruebas | C74: =Inventario_Activos!C9 -> Datos | D74: =Inventario_Activos!D9 -> Datos de prueba anonimizados | E74: Seguridad de Host | F74: Servidor de datos de prueba con controles menos estrictos que producción | G74: Compromiso del servidor de pruebas | H74: 3 | I74: 3 | J74: =H74*I74 -> 9 | K74: =INDEX(Escalas!$F$2:$F$5,MATCH(J74,Escalas!$E$2:$E$5,1)) -> Moderado | L74: =INDEX(Inventario_Activos!$I$2:$I$16,MATCH(D74,Inventario_Activos!$D$2:$D$16,0)) -> 3 | M74: =ROUND(J74*L74/5,0) -> 5 | N74: =INDEX(Escalas!$F$2:$F$5,MATCH(M74,Escalas!$E$2:$E$5,1)) -> Bajo | O74: Reducir/Mitigar | P74: Aplicar controles de seguridad equivalentes a producción, ajustados al riesgo. | Q74: =J74+(152-ROW())/100000 -> 9.00078
A75: 74 | B75: =Inventario_Activos!B9 -> Pruebas | C75: =Inventario_Activos!C9 -> Datos | D75: =Inventario_Activos!D9 -> Datos de prueba anonimizados | E75: Seguridad de Aplicación | F75: Scripts de anonimización no validados formalmente | G75: Anonimización incompleta que deja datos identificables | H75: 3 | I75: 4 | J75: =H75*I75 -> 12 | K75: =INDEX(Escalas!$F$2:$F$5,MATCH(J75,Escalas!$E$2:$E$5,1)) -> Alto | L75: =INDEX(Inventario_Activos!$I$2:$I$16,MATCH(D75,Inventario_Activos!$D$2:$D$16,0)) -> 3 | M75: =ROUND(J75*L75/5,0) -> 7 | N75: =INDEX(Escalas!$F$2:$F$5,MATCH(M75,Escalas!$E$2:$E$5,1)) -> Moderado | O75: Reducir/Mitigar | P75: Validar y auditar el proceso de anonimización antes de su uso. | Q75: =J75+(152-ROW())/100000 -> 12.00077
A76: 75 | B76: =Inventario_Activos!B9 -> Pruebas | C76: =Inventario_Activos!C9 -> Datos | D76: =Inventario_Activos!D9 -> Datos de prueba anonimizados | E76: Seguridad de Datos | F76: Proceso de anonimización reversible o débil | G76: Reidentificación de personas a partir de datos anonimizados | H76: 3 | I76: 4 | J76: =H76*I76 -> 12 | K76: =INDEX(Escalas!$F$2:$F$5,MATCH(J76,Escalas!$E$2:$E$5,1)) -> Alto | L76: =INDEX(Inventario_Activos!$I$2:$I$16,MATCH(D76,Inventario_Activos!$D$2:$D$16,0)) -> 3 | M76: =ROUND(J76*L76/5,0) -> 7 | N76: =INDEX(Escalas!$F$2:$F$5,MATCH(M76,Escalas!$E$2:$E$5,1)) -> Moderado | O76: Reducir/Mitigar | P76: Uso de técnicas robustas de anonimización/seudonimización irreversibles. | Q76: =J76+(152-ROW())/100000 -> 12.00076
A77: 76 | B77: =Inventario_Activos!B9 -> Pruebas | C77: =Inventario_Activos!C9 -> Datos | D77: =Inventario_Activos!D9 -> Datos de prueba anonimizados | E77: Gestión de Identidad y Acceso | F77: Acceso a datos de prueba sin restricción para todo el equipo de QA/desarrollo | G77: Uso indebido de datos por personal sin necesidad de acceso | H77: 3 | I77: 3 | J77: =H77*I77 -> 9 | K77: =INDEX(Escalas!$F$2:$F$5,MATCH(J77,Escalas!$E$2:$E$5,1)) -> Moderado | L77: =INDEX(Inventario_Activos!$I$2:$I$16,MATCH(D77,Inventario_Activos!$D$2:$D$16,0)) -> 3 | M77: =ROUND(J77*L77/5,0) -> 5 | N77: =INDEX(Escalas!$F$2:$F$5,MATCH(M77,Escalas!$E$2:$E$5,1)) -> Bajo | O77: Reducir/Mitigar | P77: Restringir el acceso a datos de prueba según necesidad (need-to-know). | Q77: =J77+(152-ROW())/100000 -> 9.00075
A78: 77 | B78: =Inventario_Activos!B9 -> Pruebas | C78: =Inventario_Activos!C9 -> Datos | D78: =Inventario_Activos!D9 -> Datos de prueba anonimizados | E78: Monitoreo y Respuesta | F78: Sin monitoreo del uso de datos de prueba | G78: Extracción o copia no autorizada de datos de prueba | H78: 2 | I78: 3 | J78: =H78*I78 -> 6 | K78: =INDEX(Escalas!$F$2:$F$5,MATCH(J78,Escalas!$E$2:$E$5,1)) -> Moderado | L78: =INDEX(Inventario_Activos!$I$2:$I$16,MATCH(D78,Inventario_Activos!$D$2:$D$16,0)) -> 3 | M78: =ROUND(J78*L78/5,0) -> 4 | N78: =INDEX(Escalas!$F$2:$F$5,MATCH(M78,Escalas!$E$2:$E$5,1)) -> Bajo | O78: Reducir/Mitigar | P78: Registrar y monitorear el acceso a los conjuntos de datos de prueba. | Q78: =J78+(152-ROW())/100000 -> 6.00074
A79: 78 | B79: =Inventario_Activos!B9 -> Pruebas | C79: =Inventario_Activos!C9 -> Datos | D79: =Inventario_Activos!D9 -> Datos de prueba anonimizados | E79: Continuidad y Respaldo | F79: Sin respaldo formal de los conjuntos de datos de prueba | G79: Pérdida de datasets preparados para pruebas | H79: 2 | I79: 2 | J79: =H79*I79 -> 4 | K79: =INDEX(Escalas!$F$2:$F$5,MATCH(J79,Escalas!$E$2:$E$5,1)) -> Bajo | L79: =INDEX(Inventario_Activos!$I$2:$I$16,MATCH(D79,Inventario_Activos!$D$2:$D$16,0)) -> 3 | M79: =ROUND(J79*L79/5,0) -> 2 | N79: =INDEX(Escalas!$F$2:$F$5,MATCH(M79,Escalas!$E$2:$E$5,1)) -> Bajo | O79: Aceptar | P79: Aceptar el riesgo por el bajo costo de regenerar los datos de prueba. | Q79: =J79+(152-ROW())/100000 -> 4.00073
A80: 79 | B80: =Inventario_Activos!B9 -> Pruebas | C80: =Inventario_Activos!C9 -> Datos | D80: =Inventario_Activos!D9 -> Datos de prueba anonimizados | E80: Seguridad Perimetral | F80: Datos de prueba accesibles desde ambientes no controlados (equipos personales) | G80: Fuga de datos hacia entornos externos | H80: 3 | I80: 3 | J80: =H80*I80 -> 9 | K80: =INDEX(Escalas!$F$2:$F$5,MATCH(J80,Escalas!$E$2:$E$5,1)) -> Moderado | L80: =INDEX(Inventario_Activos!$I$2:$I$16,MATCH(D80,Inventario_Activos!$D$2:$D$16,0)) -> 3 | M80: =ROUND(J80*L80/5,0) -> 5 | N80: =INDEX(Escalas!$F$2:$F$5,MATCH(M80,Escalas!$E$2:$E$5,1)) -> Bajo | O80: Reducir/Mitigar | P80: Restringir el uso de datos de prueba a entornos corporativos controlados. | Q80: =J80+(152-ROW())/100000 -> 9.00072
A81: 80 | B81: =Inventario_Activos!B9 -> Pruebas | C81: =Inventario_Activos!C9 -> Datos | D81: =Inventario_Activos!D9 -> Datos de prueba anonimizados | E81: Concientización y Procesos | F81: Falta de lineamientos claros sobre generación y uso de datos anonimizados | G81: Generación de datos de prueba inadecuadamente anonimizados | H81: 3 | I81: 3 | J81: =H81*I81 -> 9 | K81: =INDEX(Escalas!$F$2:$F$5,MATCH(J81,Escalas!$E$2:$E$5,1)) -> Moderado | L81: =INDEX(Inventario_Activos!$I$2:$I$16,MATCH(D81,Inventario_Activos!$D$2:$D$16,0)) -> 3 | M81: =ROUND(J81*L81/5,0) -> 5 | N81: =INDEX(Escalas!$F$2:$F$5,MATCH(M81,Escalas!$E$2:$E$5,1)) -> Bajo | O81: Reducir/Mitigar | P81: Guía y capacitación sobre anonimización y manejo de datos de prueba. | Q81: =J81+(152-ROW())/100000 -> 9.00071
A82: 81 | B82: =Inventario_Activos!B10 -> Pruebas | C82: =Inventario_Activos!C10 -> Recursos Humanos | D82: =Inventario_Activos!D10 -> QA Tester | E82: Seguridad Física | F82: Estación del QA sin bloqueo automático de sesión | G82: Acceso no autorizado al dejar la sesión abierta | H82: 3 | I82: 2 | J82: =H82*I82 -> 6 | K82: =INDEX(Escalas!$F$2:$F$5,MATCH(J82,Escalas!$E$2:$E$5,1)) -> Moderado | L82: =INDEX(Inventario_Activos!$I$2:$I$16,MATCH(D82,Inventario_Activos!$D$2:$D$16,0)) -> 3 | M82: =ROUND(J82*L82/5,0) -> 4 | N82: =INDEX(Escalas!$F$2:$F$5,MATCH(M82,Escalas!$E$2:$E$5,1)) -> Bajo | O82: Reducir/Mitigar | P82: Configurar bloqueo automático de pantalla tras inactividad. | Q82: =J82+(152-ROW())/100000 -> 6.0007
A83: 82 | B83: =Inventario_Activos!B10 -> Pruebas | C83: =Inventario_Activos!C10 -> Recursos Humanos | D83: =Inventario_Activos!D10 -> QA Tester | E83: Seguridad de Red | F83: QA accede a ambientes de prueba desde redes no corporativas sin VPN | G83: Exposición de accesos desde redes no confiables | H83: 3 | I83: 3 | J83: =H83*I83 -> 9 | K83: =INDEX(Escalas!$F$2:$F$5,MATCH(J83,Escalas!$E$2:$E$5,1)) -> Moderado | L83: =INDEX(Inventario_Activos!$I$2:$I$16,MATCH(D83,Inventario_Activos!$D$2:$D$16,0)) -> 3 | M83: =ROUND(J83*L83/5,0) -> 5 | N83: =INDEX(Escalas!$F$2:$F$5,MATCH(M83,Escalas!$E$2:$E$5,1)) -> Bajo | O83: Reducir/Mitigar | P83: Exigir VPN para el acceso a ambientes de prueba desde fuera de la oficina. | Q83: =J83+(152-ROW())/100000 -> 9.00069
A84: 83 | B84: =Inventario_Activos!B10 -> Pruebas | C84: =Inventario_Activos!C10 -> Recursos Humanos | D84: =Inventario_Activos!D10 -> QA Tester | E84: Seguridad de Host | F84: Estación de QA sin antivirus actualizado | G84: Infección de malware que comprometa credenciales de prueba | H84: 3 | I84: 3 | J84: =H84*I84 -> 9 | K84: =INDEX(Escalas!$F$2:$F$5,MATCH(J84,Escalas!$E$2:$E$5,1)) -> Moderado | L84: =INDEX(Inventario_Activos!$I$2:$I$16,MATCH(D84,Inventario_Activos!$D$2:$D$16,0)) -> 3 | M84: =ROUND(J84*L84/5,0) -> 5 | N84: =INDEX(Escalas!$F$2:$F$5,MATCH(M84,Escalas!$E$2:$E$5,1)) -> Bajo | O84: Reducir/Mitigar | P84: Antivirus/EDR gestionado y actualizado automáticamente. | Q84: =J84+(152-ROW())/100000 -> 9.00068
A85: 84 | B85: =Inventario_Activos!B10 -> Pruebas | C85: =Inventario_Activos!C10 -> Recursos Humanos | D85: =Inventario_Activos!D10 -> QA Tester | E85: Seguridad de Aplicación | F85: Uso de cuentas de prueba con privilegios elevados innecesarios | G85: Uso indebido de accesos de prueba con altos privilegios | H85: 3 | I85: 3 | J85: =H85*I85 -> 9 | K85: =INDEX(Escalas!$F$2:$F$5,MATCH(J85,Escalas!$E$2:$E$5,1)) -> Moderado | L85: =INDEX(Inventario_Activos!$I$2:$I$16,MATCH(D85,Inventario_Activos!$D$2:$D$16,0)) -> 3 | M85: =ROUND(J85*L85/5,0) -> 5 | N85: =INDEX(Escalas!$F$2:$F$5,MATCH(M85,Escalas!$E$2:$E$5,1)) -> Bajo | O85: Reducir/Mitigar | P85: Asignar a QA solo los privilegios necesarios para las pruebas. | Q85: =J85+(152-ROW())/100000 -> 9.00067
A86: 85 | B86: =Inventario_Activos!B10 -> Pruebas | C86: =Inventario_Activos!C10 -> Recursos Humanos | D86: =Inventario_Activos!D10 -> QA Tester | E86: Seguridad de Datos | F86: QA maneja datos de prueba potencialmente sensibles sin lineamientos | G86: Divulgación accidental de información en reportes de bugs | H86: 3 | I86: 3 | J86: =H86*I86 -> 9 | K86: =INDEX(Escalas!$F$2:$F$5,MATCH(J86,Escalas!$E$2:$E$5,1)) -> Moderado | L86: =INDEX(Inventario_Activos!$I$2:$I$16,MATCH(D86,Inventario_Activos!$D$2:$D$16,0)) -> 3 | M86: =ROUND(J86*L86/5,0) -> 5 | N86: =INDEX(Escalas!$F$2:$F$5,MATCH(M86,Escalas!$E$2:$E$5,1)) -> Bajo | O86: Reducir/Mitigar | P86: Lineamientos de manejo de datos sensibles en reportes y evidencias de prueba. | Q86: =J86+(152-ROW())/100000 -> 9.00066
A87: 86 | B87: =Inventario_Activos!B10 -> Pruebas | C87: =Inventario_Activos!C10 -> Recursos Humanos | D87: =Inventario_Activos!D10 -> QA Tester | E87: Gestión de Identidad y Acceso | F87: Credenciales de prueba compartidas entre varios testers | G87: Falta de trazabilidad de acciones realizadas | H87: 3 | I87: 3 | J87: =H87*I87 -> 9 | K87: =INDEX(Escalas!$F$2:$F$5,MATCH(J87,Escalas!$E$2:$E$5,1)) -> Moderado | L87: =INDEX(Inventario_Activos!$I$2:$I$16,MATCH(D87,Inventario_Activos!$D$2:$D$16,0)) -> 3 | M87: =ROUND(J87*L87/5,0) -> 5 | N87: =INDEX(Escalas!$F$2:$F$5,MATCH(M87,Escalas!$E$2:$E$5,1)) -> Bajo | O87: Reducir/Mitigar | P87: Credenciales individuales para cada tester. | Q87: =J87+(152-ROW())/100000 -> 9.00065
A88: 87 | B88: =Inventario_Activos!B10 -> Pruebas | C88: =Inventario_Activos!C10 -> Recursos Humanos | D88: =Inventario_Activos!D10 -> QA Tester | E88: Monitoreo y Respuesta | F88: Actividad del rol de QA no se audita | G88: Uso indebido de accesos de prueba sin detección | H88: 2 | I88: 3 | J88: =H88*I88 -> 6 | K88: =INDEX(Escalas!$F$2:$F$5,MATCH(J88,Escalas!$E$2:$E$5,1)) -> Moderado | L88: =INDEX(Inventario_Activos!$I$2:$I$16,MATCH(D88,Inventario_Activos!$D$2:$D$16,0)) -> 3 | M88: =ROUND(J88*L88/5,0) -> 4 | N88: =INDEX(Escalas!$F$2:$F$5,MATCH(M88,Escalas!$E$2:$E$5,1)) -> Bajo | O88: Reducir/Mitigar | P88: Incluir las cuentas de QA en el monitoreo de actividad general. | Q88: =J88+(152-ROW())/100000 -> 6.00064
A89: 88 | B89: =Inventario_Activos!B10 -> Pruebas | C89: =Inventario_Activos!C10 -> Recursos Humanos | D89: =Inventario_Activos!D10 -> QA Tester | E89: Continuidad y Respaldo | F89: Dependencia de un solo tester para casos de prueba críticos | G89: Retraso en pruebas críticas ante ausencia del tester | H89: 3 | I89: 2 | J89: =H89*I89 -> 6 | K89: =INDEX(Escalas!$F$2:$F$5,MATCH(J89,Escalas!$E$2:$E$5,1)) -> Moderado | L89: =INDEX(Inventario_Activos!$I$2:$I$16,MATCH(D89,Inventario_Activos!$D$2:$D$16,0)) -> 3 | M89: =ROUND(J89*L89/5,0) -> 4 | N89: =INDEX(Escalas!$F$2:$F$5,MATCH(M89,Escalas!$E$2:$E$5,1)) -> Bajo | O89: Reducir/Mitigar | P89: Documentar casos de prueba y capacitar a más de una persona. | Q89: =J89+(152-ROW())/100000 -> 6.00063
A90: 89 | B90: =Inventario_Activos!B10 -> Pruebas | C90: =Inventario_Activos!C10 -> Recursos Humanos | D90: =Inventario_Activos!D10 -> QA Tester | E90: Seguridad Perimetral | F90: Acceso de QA a sistemas de producción para validar incidentes | G90: Uso indebido de accesos de prueba en el ambiente productivo | H90: 2 | I90: 4 | J90: =H90*I90 -> 8 | K90: =INDEX(Escalas!$F$2:$F$5,MATCH(J90,Escalas!$E$2:$E$5,1)) -> Moderado | L90: =INDEX(Inventario_Activos!$I$2:$I$16,MATCH(D90,Inventario_Activos!$D$2:$D$16,0)) -> 3 | M90: =ROUND(J90*L90/5,0) -> 5 | N90: =INDEX(Escalas!$F$2:$F$5,MATCH(M90,Escalas!$E$2:$E$5,1)) -> Bajo | O90: Reducir/Mitigar | P90: Prohibir el acceso de QA a producción y usar réplicas para validación. | Q90: =J90+(152-ROW())/100000 -> 8.00062
A91: 90 | B91: =Inventario_Activos!B10 -> Pruebas | C91: =Inventario_Activos!C10 -> Recursos Humanos | D91: =Inventario_Activos!D10 -> QA Tester | E91: Concientización y Procesos | F91: Falta de capacitación en seguridad para el equipo de QA | G91: Reporte inadecuado de vulnerabilidades encontradas (fuga de información) | H91: 3 | I91: 3 | J91: =H91*I91 -> 9 | K91: =INDEX(Escalas!$F$2:$F$5,MATCH(J91,Escalas!$E$2:$E$5,1)) -> Moderado | L91: =INDEX(Inventario_Activos!$I$2:$I$16,MATCH(D91,Inventario_Activos!$D$2:$D$16,0)) -> 3 | M91: =ROUND(J91*L91/5,0) -> 5 | N91: =INDEX(Escalas!$F$2:$F$5,MATCH(M91,Escalas!$E$2:$E$5,1)) -> Bajo | O91: Reducir/Mitigar | P91: Capacitar al equipo de QA en manejo responsable de hallazgos de seguridad. | Q91: =J91+(152-ROW())/100000 -> 9.00061
A92: 91 | B92: =Inventario_Activos!B11 -> Pruebas | C92: =Inventario_Activos!C11 -> Software | D92: =Inventario_Activos!D11 -> Herramienta de automatización de pruebas | E92: Seguridad Física | F92: Servidor de la herramienta de automatización sin acceso restringido | G92: Acceso físico no autorizado | H92: 2 | I92: 2 | J92: =H92*I92 -> 4 | K92: =INDEX(Escalas!$F$2:$F$5,MATCH(J92,Escalas!$E$2:$E$5,1)) -> Bajo | L92: =INDEX(Inventario_Activos!$I$2:$I$16,MATCH(D92,Inventario_Activos!$D$2:$D$16,0)) -> 3 | M92: =ROUND(J92*L92/5,0) -> 2 | N92: =INDEX(Escalas!$F$2:$F$5,MATCH(M92,Escalas!$E$2:$E$5,1)) -> Bajo | O92: Aceptar | P92: Aceptar el riesgo por bajo impacto, o ubicar el servidor en área restringida. | Q92: =J92+(152-ROW())/100000 -> 4.0006
A93: 92 | B93: =Inventario_Activos!B11 -> Pruebas | C93: =Inventario_Activos!C11 -> Software | D93: =Inventario_Activos!D11 -> Herramienta de automatización de pruebas | E93: Seguridad de Red | F93: Herramienta de automatización accesible desde toda la red sin segmentación | G93: Acceso no autorizado a scripts y resultados de prueba | H93: 2 | I93: 3 | J93: =H93*I93 -> 6 | K93: =INDEX(Escalas!$F$2:$F$5,MATCH(J93,Escalas!$E$2:$E$5,1)) -> Moderado | L93: =INDEX(Inventario_Activos!$I$2:$I$16,MATCH(D93,Inventario_Activos!$D$2:$D$16,0)) -> 3 | M93: =ROUND(J93*L93/5,0) -> 4 | N93: =INDEX(Escalas!$F$2:$F$5,MATCH(M93,Escalas!$E$2:$E$5,1)) -> Bajo | O93: Reducir/Mitigar | P93: Restringir acceso mediante VLAN y control de firewall. | Q93: =J93+(152-ROW())/100000 -> 6.00059
A94: 93 | B94: =Inventario_Activos!B11 -> Pruebas | C94: =Inventario_Activos!C11 -> Software | D94: =Inventario_Activos!D11 -> Herramienta de automatización de pruebas | E94: Seguridad de Host | F94: Servidor con dependencias y librerías desactualizadas | G94: Explotación de vulnerabilidades en librerías de automatización | H94: 3 | I94: 3 | J94: =H94*I94 -> 9 | K94: =INDEX(Escalas!$F$2:$F$5,MATCH(J94,Escalas!$E$2:$E$5,1)) -> Moderado | L94: =INDEX(Inventario_Activos!$I$2:$I$16,MATCH(D94,Inventario_Activos!$D$2:$D$16,0)) -> 3 | M94: =ROUND(J94*L94/5,0) -> 5 | N94: =INDEX(Escalas!$F$2:$F$5,MATCH(M94,Escalas!$E$2:$E$5,1)) -> Bajo | O94: Reducir/Mitigar | P94: Actualización periódica de dependencias y escaneo de vulnerabilidades (SCA). | Q94: =J94+(152-ROW())/100000 -> 9.00058
A95: 94 | B95: =Inventario_Activos!B11 -> Pruebas | C95: =Inventario_Activos!C11 -> Software | D95: =Inventario_Activos!D11 -> Herramienta de automatización de pruebas | E95: Seguridad de Aplicación | F95: Scripts de automatización con credenciales embebidas en texto plano | G95: Exposición de credenciales de otros sistemas | H95: 4 | I95: 4 | J95: =H95*I95 -> 16 | K95: =INDEX(Escalas!$F$2:$F$5,MATCH(J95,Escalas!$E$2:$E$5,1)) -> Alto | L95: =INDEX(Inventario_Activos!$I$2:$I$16,MATCH(D95,Inventario_Activos!$D$2:$D$16,0)) -> 3 | M95: =ROUND(J95*L95/5,0) -> 10 | N95: =INDEX(Escalas!$F$2:$F$5,MATCH(M95,Escalas!$E$2:$E$5,1)) -> Moderado | O95: Reducir/Mitigar | P95: Uso de gestor de secretos (vault) para credenciales de pruebas. | Q95: =J95+(152-ROW())/100000 -> 16.00057
A96: 95 | B96: =Inventario_Activos!B11 -> Pruebas | C96: =Inventario_Activos!C11 -> Software | D96: =Inventario_Activos!D11 -> Herramienta de automatización de pruebas | E96: Seguridad de Datos | F96: Resultados de pruebas almacenan datos sensibles sin protección | G96: Exposición de información al compartir reportes | H96: 3 | I96: 3 | J96: =H96*I96 -> 9 | K96: =INDEX(Escalas!$F$2:$F$5,MATCH(J96,Escalas!$E$2:$E$5,1)) -> Moderado | L96: =INDEX(Inventario_Activos!$I$2:$I$16,MATCH(D96,Inventario_Activos!$D$2:$D$16,0)) -> 3 | M96: =ROUND(J96*L96/5,0) -> 5 | N96: =INDEX(Escalas!$F$2:$F$5,MATCH(M96,Escalas!$E$2:$E$5,1)) -> Bajo | O96: Reducir/Mitigar | P96: Enmascarar datos sensibles en los reportes generados. | Q96: =J96+(152-ROW())/100000 -> 9.00056
A97: 96 | B97: =Inventario_Activos!B11 -> Pruebas | C97: =Inventario_Activos!C11 -> Software | D97: =Inventario_Activos!D11 -> Herramienta de automatización de pruebas | E97: Gestión de Identidad y Acceso | F97: Cuenta de servicio con privilegios elevados para ejecutar pruebas | G97: Abuso de la cuenta de servicio para acceso indebido | H97: 3 | I97: 4 | J97: =H97*I97 -> 12 | K97: =INDEX(Escalas!$F$2:$F$5,MATCH(J97,Escalas!$E$2:$E$5,1)) -> Alto | L97: =INDEX(Inventario_Activos!$I$2:$I$16,MATCH(D97,Inventario_Activos!$D$2:$D$16,0)) -> 3 | M97: =ROUND(J97*L97/5,0) -> 7 | N97: =INDEX(Escalas!$F$2:$F$5,MATCH(M97,Escalas!$E$2:$E$5,1)) -> Moderado | O97: Reducir/Mitigar | P97: Limitar privilegios de la cuenta de servicio al mínimo necesario. | Q97: =J97+(152-ROW())/100000 -> 12.00055
A98: 97 | B98: =Inventario_Activos!B11 -> Pruebas | C98: =Inventario_Activos!C11 -> Software | D98: =Inventario_Activos!D11 -> Herramienta de automatización de pruebas | E98: Monitoreo y Respuesta | F98: No se audita el uso de la herramienta de automatización | G98: Ejecuciones no autorizadas sin detección | H98: 2 | I98: 3 | J98: =H98*I98 -> 6 | K98: =INDEX(Escalas!$F$2:$F$5,MATCH(J98,Escalas!$E$2:$E$5,1)) -> Moderado | L98: =INDEX(Inventario_Activos!$I$2:$I$16,MATCH(D98,Inventario_Activos!$D$2:$D$16,0)) -> 3 | M98: =ROUND(J98*L98/5,0) -> 4 | N98: =INDEX(Escalas!$F$2:$F$5,MATCH(M98,Escalas!$E$2:$E$5,1)) -> Bajo | O98: Reducir/Mitigar | P98: Habilitar auditoría de ejecuciones y accesos. | Q98: =J98+(152-ROW())/100000 -> 6.00054
A99: 98 | B99: =Inventario_Activos!B11 -> Pruebas | C99: =Inventario_Activos!C11 -> Software | D99: =Inventario_Activos!D11 -> Herramienta de automatización de pruebas | E99: Continuidad y Respaldo | F99: Configuración de pruebas sin versionado ni respaldo | G99: Pérdida de suites de prueba desarrolladas | H99: 3 | I99: 3 | J99: =H99*I99 -> 9 | K99: =INDEX(Escalas!$F$2:$F$5,MATCH(J99,Escalas!$E$2:$E$5,1)) -> Moderado | L99: =INDEX(Inventario_Activos!$I$2:$I$16,MATCH(D99,Inventario_Activos!$D$2:$D$16,0)) -> 3 | M99: =ROUND(J99*L99/5,0) -> 5 | N99: =INDEX(Escalas!$F$2:$F$5,MATCH(M99,Escalas!$E$2:$E$5,1)) -> Bajo | O99: Reducir/Mitigar | P99: Versionar la configuración en el repositorio de código. | Q99: =J99+(152-ROW())/100000 -> 9.00053
A100: 99 | B100: =Inventario_Activos!B11 -> Pruebas | C100: =Inventario_Activos!C11 -> Software | D100: =Inventario_Activos!D11 -> Herramienta de automatización de pruebas | E100: Seguridad Perimetral | F100: Integración con sistemas externos (CI/CD) sin control de acceso | G100: Uso de la herramienta como puente hacia otros sistemas | H100: 3 | I100: 4 | J100: =H100*I100 -> 12 | K100: =INDEX(Escalas!$F$2:$F$5,MATCH(J100,Escalas!$E$2:$E$5,1)) -> Alto | L100: =INDEX(Inventario_Activos!$I$2:$I$16,MATCH(D100,Inventario_Activos!$D$2:$D$16,0)) -> 3 | M100: =ROUND(J100*L100/5,0) -> 7 | N100: =INDEX(Escalas!$F$2:$F$5,MATCH(M100,Escalas!$E$2:$E$5,1)) -> Moderado | O100: Reducir/Mitigar | P100: Restringir y auditar las integraciones externas. | Q100: =J100+(152-ROW())/100000 -> 12.00052
...

Sheet Matriz_Calor
A1: Matriz de Calor — Frecuencia de Riesgos por Probabilidad x Impacto
A3: Probabilidad \ Impacto | B3: 1 | C3: 2 | D3: 3 | E3: 4 | F3: 5
A4: 1 | B4: =COUNTIFS(Riesgos!$H$2:$H$151,1,Riesgos!$I$2:$I$151,1) -> 0 | C4: =COUNTIFS(Riesgos!$H$2:$H$151,1,Riesgos!$I$2:$I$151,2) -> 0 | D4: =COUNTIFS(Riesgos!$H$2:$H$151,1,Riesgos!$I$2:$I$151,3) -> 0 | E4: =COUNTIFS(Riesgos!$H$2:$H$151,1,Riesgos!$I$2:$I$151,4) -> 0 | F4: =COUNTIFS(Riesgos!$H$2:$H$151,1,Riesgos!$I$2:$I$151,5) -> 0
A5: 2 | B5: =COUNTIFS(Riesgos!$H$2:$H$151,2,Riesgos!$I$2:$I$151,1) -> 0 | C5: =COUNTIFS(Riesgos!$H$2:$H$151,2,Riesgos!$I$2:$I$151,2) -> 7 | D5: =COUNTIFS(Riesgos!$H$2:$H$151,2,Riesgos!$I$2:$I$151,3) -> 12 | E5: =COUNTIFS(Riesgos!$H$2:$H$151,2,Riesgos!$I$2:$I$151,4) -> 11 | F5: =COUNTIFS(Riesgos!$H$2:$H$151,2,Riesgos!$I$2:$I$151,5) -> 9
A6: 3 | B6: =COUNTIFS(Riesgos!$H$2:$H$151,3,Riesgos!$I$2:$I$151,1) -> 0 | C6: =COUNTIFS(Riesgos!$H$2:$H$151,3,Riesgos!$I$2:$I$151,2) -> 3 | D6: =COUNTIFS(Riesgos!$H$2:$H$151,3,Riesgos!$I$2:$I$151,3) -> 32 | E6: =COUNTIFS(Riesgos!$H$2:$H$151,3,Riesgos!$I$2:$I$151,4) -> 43 | F6: =COUNTIFS(Riesgos!$H$2:$H$151,3,Riesgos!$I$2:$I$151,5) -> 26
A7: 4 | B7: =COUNTIFS(Riesgos!$H$2:$H$151,4,Riesgos!$I$2:$I$151,1) -> 0 | C7: =COUNTIFS(Riesgos!$H$2:$H$151,4,Riesgos!$I$2:$I$151,2) -> 0 | D7: =COUNTIFS(Riesgos!$H$2:$H$151,4,Riesgos!$I$2:$I$151,3) -> 0 | E7: =COUNTIFS(Riesgos!$H$2:$H$151,4,Riesgos!$I$2:$I$151,4) -> 6 | F7: =COUNTIFS(Riesgos!$H$2:$H$151,4,Riesgos!$I$2:$I$151,5) -> 1
A8: 5 | B8: =COUNTIFS(Riesgos!$H$2:$H$151,5,Riesgos!$I$2:$I$151,1) -> 0 | C8: =COUNTIFS(Riesgos!$H$2:$H$151,5,Riesgos!$I$2:$I$151,2) -> 0 | D8: =COUNTIFS(Riesgos!$H$2:$H$151,5,Riesgos!$I$2:$I$151,3) -> 0 | E8: =COUNTIFS(Riesgos!$H$2:$H$151,5,Riesgos!$I$2:$I$151,4) -> 0 | F8: =COUNTIFS(Riesgos!$H$2:$H$151,5,Riesgos!$I$2:$I$151,5) -> 0
A10: Total de riesgos registrados: | B10: =COUNTA(Riesgos!$A$2:$A$151) -> 150
A12: Resumen por Nivel MAGERIT | D12: Resumen por Nivel OCTAVE
A13: Nivel | B13: Cantidad de riesgos | D13: Nivel | E13: Cantidad de riesgos
A14: Bajo | B14: =COUNTIF(Riesgos!$K$2:$K$151,"Bajo") -> 7 | D14: Bajo | E14: =COUNTIF(Riesgos!$N$2:$N$151,"Bajo") -> 64
A15: Moderado | B15: =COUNTIF(Riesgos!$K$2:$K$151,"Moderado") -> 67 | D15: Moderado | E15: =COUNTIF(Riesgos!$N$2:$N$151,"Moderado") -> 78
A16: Alto | B16: =COUNTIF(Riesgos!$K$2:$K$151,"Alto") -> 76 | D16: Alto | E16: =COUNTIF(Riesgos!$N$2:$N$151,"Alto") -> 8
A17: Crítico | B17: =COUNTIF(Riesgos!$K$2:$K$151,"Crítico") -> 0 | D17: Crítico | E17: =COUNTIF(Riesgos!$N$2:$N$151,"Crítico") -> 0

Sheet Tratamiento
A1: No | B1: Activo | C1: Criticidad del Activo | D1: Riesgos Bajo | E1: Riesgos Moderado | F1: Riesgos Alto | G1: Riesgos Crítico | H1: Prioridad de Tratamiento
A2: 1 | B2: =Inventario_Activos!D2 -> Servidor de Base de Datos | C2: =Inventario_Activos!I2 -> 5 | D2: =COUNTIFS(Riesgos!$D$2:$D$151,B2,Riesgos!$K$2:$K$151,"Bajo") -> 0 | E2: =COUNTIFS(Riesgos!$D$2:$D$151,B2,Riesgos!$K$2:$K$151,"Moderado") -> 3 | F2: =COUNTIFS(Riesgos!$D$2:$D$151,B2,Riesgos!$K$2:$K$151,"Alto") -> 7 | G2: =COUNTIFS(Riesgos!$D$2:$D$151,B2,Riesgos!$K$2:$K$151,"Crítico") -> 0 | H2: =IF(G2>0,"Prioridad Muy Alta",IF(F2>0,"Prioridad Alta",IF(E2>0,"Prioridad Media","Prioridad Baja"))) -> Prioridad Alta
A3: 2 | B3: =Inventario_Activos!D3 -> Sistema ERP / Facturación | C3: =Inventario_Activos!I3 -> 3 | D3: =COUNTIFS(Riesgos!$D$2:$D$151,B3,Riesgos!$K$2:$K$151,"Bajo") -> 0 | E3: =COUNTIFS(Riesgos!$D$2:$D$151,B3,Riesgos!$K$2:$K$151,"Moderado") -> 4 | F3: =COUNTIFS(Riesgos!$D$2:$D$151,B3,Riesgos!$K$2:$K$151,"Alto") -> 6 | G3: =COUNTIFS(Riesgos!$D$2:$D$151,B3,Riesgos!$K$2:$K$151,"Crítico") -> 0 | H3: =IF(G3>0,"Prioridad Muy Alta",IF(F3>0,"Prioridad Alta",IF(E3>0,"Prioridad Media","Prioridad Baja"))) -> Prioridad Alta
A4: 3 | B4: =Inventario_Activos!D4 -> Datos de clientes | C4: =Inventario_Activos!I4 -> 3 | D4: =COUNTIFS(Riesgos!$D$2:$D$151,B4,Riesgos!$K$2:$K$151,"Bajo") -> 0 | E4: =COUNTIFS(Riesgos!$D$2:$D$151,B4,Riesgos!$K$2:$K$151,"Moderado") -> 3 | F4: =COUNTIFS(Riesgos!$D$2:$D$151,B4,Riesgos!$K$2:$K$151,"Alto") -> 7 | G4: =COUNTIFS(Riesgos!$D$2:$D$151,B4,Riesgos!$K$2:$K$151,"Crítico") -> 0 | H4: =IF(G4>0,"Prioridad Muy Alta",IF(F4>0,"Prioridad Alta",IF(E4>0,"Prioridad Media","Prioridad Baja"))) -> Prioridad Alta
A5: 4 | B5: =Inventario_Activos!D5 -> Administrador de sistemas | C5: =Inventario_Activos!I5 -> 3 | D5: =COUNTIFS(Riesgos!$D$2:$D$151,B5,Riesgos!$K$2:$K$151,"Bajo") -> 0 | E5: =COUNTIFS(Riesgos!$D$2:$D$151,B5,Riesgos!$K$2:$K$151,"Moderado") -> 3 | F5: =COUNTIFS(Riesgos!$D$2:$D$151,B5,Riesgos!$K$2:$K$151,"Alto") -> 7 | G5: =COUNTIFS(Riesgos!$D$2:$D$151,B5,Riesgos!$K$2:$K$151,"Crítico") -> 0 | H5: =IF(G5>0,"Prioridad Muy Alta",IF(F5>0,"Prioridad Alta",IF(E5>0,"Prioridad Media","Prioridad Baja"))) -> Prioridad Alta
A6: 5 | B6: =Inventario_Activos!D6 -> Firewall / Router de borde | C6: =Inventario_Activos!I6 -> 3 | D6: =COUNTIFS(Riesgos!$D$2:$D$151,B6,Riesgos!$K$2:$K$151,"Bajo") -> 0 | E6: =COUNTIFS(Riesgos!$D$2:$D$151,B6,Riesgos!$K$2:$K$151,"Moderado") -> 4 | F6: =COUNTIFS(Riesgos!$D$2:$D$151,B6,Riesgos!$K$2:$K$151,"Alto") -> 6 | G6: =COUNTIFS(Riesgos!$D$2:$D$151,B6,Riesgos!$K$2:$K$151,"Crítico") -> 0 | H6: =IF(G6>0,"Prioridad Muy Alta",IF(F6>0,"Prioridad Alta",IF(E6>0,"Prioridad Media","Prioridad Baja"))) -> Prioridad Alta
A7: 6 | B7: =Inventario_Activos!D7 -> Servidor de pruebas | C7: =Inventario_Activos!I7 -> 3 | D7: =COUNTIFS(Riesgos!$D$2:$D$151,B7,Riesgos!$K$2:$K$151,"Bajo") -> 2 | E7: =COUNTIFS(Riesgos!$D$2:$D$151,B7,Riesgos!$K$2:$K$151,"Moderado") -> 5 | F7: =COUNTIFS(Riesgos!$D$2:$D$151,B7,Riesgos!$K$2:$K$151,"Alto") -> 3 | G7: =COUNTIFS(Riesgos!$D$2:$D$151,B7,Riesgos!$K$2:$K$151,"Crítico") -> 0 | H7: =IF(G7>0,"Prioridad Muy Alta",IF(F7>0,"Prioridad Alta",IF(E7>0,"Prioridad Media","Prioridad Baja"))) -> Prioridad Alta
A8: 7 | B8: =Inventario_Activos!D8 -> Ambiente de staging web | C8: =Inventario_Activos!I8 -> 3 | D8: =COUNTIFS(Riesgos!$D$2:$D$151,B8,Riesgos!$K$2:$K$151,"Bajo") -> 2 | E8: =COUNTIFS(Riesgos!$D$2:$D$151,B8,Riesgos!$K$2:$K$151,"Moderado") -> 4 | F8: =COUNTIFS(Riesgos!$D$2:$D$151,B8,Riesgos!$K$2:$K$151,"Alto") -> 4 | G8: =COUNTIFS(Riesgos!$D$2:$D$151,B8,Riesgos!$K$2:$K$151,"Crítico") -> 0 | H8: =IF(G8>0,"Prioridad Muy Alta",IF(F8>0,"Prioridad Alta",IF(E8>0,"Prioridad Media","Prioridad Baja"))) -> Prioridad Alta
A9: 8 | B9: =Inventario_Activos!D9 -> Datos de prueba anonimizados | C9: =Inventario_Activos!I9 -> 3 | D9: =COUNTIFS(Riesgos!$D$2:$D$151,B9,Riesgos!$K$2:$K$151,"Bajo") -> 2 | E9: =COUNTIFS(Riesgos!$D$2:$D$151,B9,Riesgos!$K$2:$K$151,"Moderado") -> 6 | F9: =COUNTIFS(Riesgos!$D$2:$D$151,B9,Riesgos!$K$2:$K$151,"Alto") -> 2 | G9: =COUNTIFS(Riesgos!$D$2:$D$151,B9,Riesgos!$K$2:$K$151,"Crítico") -> 0 | H9: =IF(G9>0,"Prioridad Muy Alta",IF(F9>0,"Prioridad Alta",IF(E9>0,"Prioridad Media","Prioridad Baja"))) -> Prioridad Alta
A10: 9 | B10: =Inventario_Activos!D10 -> QA Tester | C10: =Inventario_Activos!I10 -> 3 | D10: =COUNTIFS(Riesgos!$D$2:$D$151,B10,Riesgos!$K$2:$K$151,"Bajo") -> 0 | E10: =COUNTIFS(Riesgos!$D$2:$D$151,B10,Riesgos!$K$2:$K$151,"Moderado") -> 10 | F10: =COUNTIFS(Riesgos!$D$2:$D$151,B10,Riesgos!$K$2:$K$151,"Alto") -> 0 | G10: =COUNTIFS(Riesgos!$D$2:$D$151,B10,Riesgos!$K$2:$K$151,"Crítico") -> 0 | H10: =IF(G10>0,"Prioridad Muy Alta",IF(F10>0,"Prioridad Alta",IF(E10>0,"Prioridad Media","Prioridad Baja"))) -> Prioridad Media
A11: 10 | B11: =Inventario_Activos!D11 -> Herramienta de automatización de pruebas | C11: =Inventario_Activos!I11 -> 3 | D11: =COUNTIFS(Riesgos!$D$2:$D$151,B11,Riesgos!$K$2:$K$151,"Bajo") -> 1 | E11: =COUNTIFS(Riesgos!$D$2:$D$151,B11,Riesgos!$K$2:$K$151,"Moderado") -> 6 | F11: =COUNTIFS(Riesgos!$D$2:$D$151,B11,Riesgos!$K$2:$K$151,"Alto") -> 3 | G11: =COUNTIFS(Riesgos!$D$2:$D$151,B11,Riesgos!$K$2:$K$151,"Crítico") -> 0 | H11: =IF(G11>0,"Prioridad Muy Alta",IF(F11>0,"Prioridad Alta",IF(E11>0,"Prioridad Media","Prioridad Baja"))) -> Prioridad Alta
A12: 11 | B12: =Inventario_Activos!D12 -> Estación de trabajo del desarrollador | C12: =Inventario_Activos!I12 -> 3 | D12: =COUNTIFS(Riesgos!$D$2:$D$151,B12,Riesgos!$K$2:$K$151,"Bajo") -> 0 | E12: =COUNTIFS(Riesgos!$D$2:$D$151,B12,Riesgos!$K$2:$K$151,"Moderado") -> 7 | F12: =COUNTIFS(Riesgos!$D$2:$D$151,B12,Riesgos!$K$2:$K$151,"Alto") -> 3 | G12: =COUNTIFS(Riesgos!$D$2:$D$151,B12,Riesgos!$K$2:$K$151,"Crítico") -> 0 | H12: =IF(G12>0,"Prioridad Muy Alta",IF(F12>0,"Prioridad Alta",IF(E12>0,"Prioridad Media","Prioridad Baja"))) -> Prioridad Alta
A13: 12 | B13: =Inventario_Activos!D13 -> Repositorio de código (Git) | C13: =Inventario_Activos!I13 -> 3 | D13: =COUNTIFS(Riesgos!$D$2:$D$151,B13,Riesgos!$K$2:$K$151,"Bajo") -> 0 | E13: =COUNTIFS(Riesgos!$D$2:$D$151,B13,Riesgos!$K$2:$K$151,"Moderado") -> 5 | F13: =COUNTIFS(Riesgos!$D$2:$D$151,B13,Riesgos!$K$2:$K$151,"Alto") -> 5 | G13: =COUNTIFS(Riesgos!$D$2:$D$151,B13,Riesgos!$K$2:$K$151,"Crítico") -> 0 | H13: =IF(G13>0,"Prioridad Muy Alta",IF(F13>0,"Prioridad Alta",IF(E13>0,"Prioridad Media","Prioridad Baja"))) -> Prioridad Alta
... A16: 15 | B16: =Inventario_Activos!D16 -> Entorno IDE / CI-CD | C16: =Inventario_Activos!I16 -> 3 | D16: =COUNTIFS(Riesgos!$D$2:$D$151,B16,Riesgos!$K$2:$K$151,"Bajo") -> 0 | E16: =COUNTIFS(Riesgos!$D$2:$D$151,B16,Riesgos!$K$2:$K$151,"Moderado") -> 3 | F16: =COUNTIFS(Riesgos!$D$2:$D$151,B16,Riesgos!$K$2:$K$151,"Alto") -> 7 | G16: =COUNTIFS(Riesgos!$D$2:$D$151,B16,Riesgos!$K$2:$K$151,"Crítico") -> 0 | H16: =IF(G16>0,"Prioridad Muy Alta",IF(F16>0,"Prioridad Alta",IF(E16>0,"Prioridad Media","Prioridad Baja"))) -> Prioridad Alta

Sheet Escalas
A1: Escala de Probabilidad / Impacto (1-5) | E1: Niveles de Riesgo (MAGERIT / OCTAVE)
A2: Valor | B2: Descripción | E2: Límite inferior | F2: Nivel | G2: Color
A3: 1 | B3: Muy baja | E3: 1 | F3: Bajo | G3: Verde
A4: 2 | B4: Baja | E4: 6 | F4: Moderado | G4: Amarillo
A5: 3 | B5: Media | E5: 11 | F5: Alto | G5: Naranja
A6: 4 | B6: Alta | E6: 16 | F6: Crítico | G6: Rojo
A7: 5 | B7: Muy alta
A9: Criticidad de Activos (1-5) | E9: Tratamiento de Riesgo
A10: Límite inferior | B10: Clasificación | E10: Evitar
A11: 1 | B11: Baja | E11: Reducir/Mitigar
A12: 2 | B12: Media | E12: Transferir
A13: 4 | B13: Alta | E13: Aceptar
A14: 5 | B14: Muy alta

Sheet Top10_y_Graficas
B2: TOP 10 RIESGOS MÁS CRÍTICOS Y GRÁFICAS DE RESUMEN
B3: Los 10 riesgos con mayor puntaje de Riesgo MAGERIT (Probabilidad x Impacto), calculados automáticamente desde la hoja Riesgos.
B5: Puesto | C5: Ambiente | D5: Activo | E5: Capa de Seguridad | F5: Amenaza | G5: Prob. | H5: Impacto | I5: Riesgo MAGERIT | J5: Nivel MAGERIT | K5: Riesgo OCTAVE | L5: Nivel OCTAVE | M5: Tratamiento
B6: 1 | C6: =INDEX(Riesgos!$B$2:$B$151,MATCH(LARGE(Riesgos!$Q$2:$Q$151,1),Riesgos!$Q$2:$Q$151,0)) -> Desarrollo | D6: =INDEX(Riesgos!$D$2:$D$151,MATCH(LARGE(Riesgos!$Q$2:$Q$151,1),Riesgos!$Q$2:$Q$151,0)) -> Código fuente y credenciales | E6: =INDEX(Riesgos!$E$2:$E$151,MATCH(LARGE(Riesgos!$Q$2:$Q$151,1),Riesgos!$Q$2:$Q$151,0)) -> Seguridad de Aplicación | F6: =INDEX(Riesgos!$G$2:$G$151,MATCH(LARGE(Riesgos!$Q$2:$Q$151,1),Riesgos!$Q$2:$Q$151,0)) -> Exposición de credenciales al compartir o publicar el código | G6: =INDEX(Riesgos!$H$2:$H$151,MATCH(LARGE(Riesgos!$Q$2:$Q$151,1),Riesgos!$Q$2:$Q$151,0)) -> 4 | H6: =INDEX(Riesgos!$I$2:$I$151,MATCH(LARGE(Riesgos!$Q$2:$Q$151,1),Riesgos!$Q$2:$Q$151,0)) -> 5 | I6: =INDEX(Riesgos!$J$2:$J$151,MATCH(LARGE(Riesgos!$Q$2:$Q$151,1),Riesgos!$Q$2:$Q$151,0)) -> 20 | J6: =INDEX(Riesgos!$K$2:$K$151,MATCH(LARGE(Riesgos!$Q$2:$Q$151,1),Riesgos!$Q$2:$Q$151,0)) -> Alto | K6: =INDEX(Riesgos!$M$2:$M$151,MATCH(LARGE(Riesgos!$Q$2:$Q$151,1),Riesgos!$Q$2:$Q$151,0)) -> 12 | L6: =INDEX(Riesgos!$N$2:$N$151,MATCH(LARGE(Riesgos!$Q$2:$Q$151,1),Riesgos!$Q$2:$Q$151,0)) -> Alto | M6: =INDEX(Riesgos!$O$2:$O$151,MATCH(LARGE(Riesgos!$Q$2:$Q$151,1),Riesgos!$Q$2:$Q$151,0)) -> Reducir/Mitigar
B7: 2 | C7: =INDEX(Riesgos!$B$2:$B$151,MATCH(LARGE(Riesgos!$Q$2:$Q$151,2),Riesgos!$Q$2:$Q$151,0)) -> Producción | D7: =INDEX(Riesgos!$D$2:$D$151,MATCH(LARGE(Riesgos!$Q$2:$Q$151,2),Riesgos!$Q$2:$Q$151,0)) -> Servidor de Base de Datos | E7: =INDEX(Riesgos!$E$2:$E$151,MATCH(LARGE(Riesgos!$Q$2:$Q$151,2),Riesgos!$Q$2:$Q$151,0)) -> Seguridad de Host | F7: =INDEX(Riesgos!$G$2:$G$151,MATCH(LARGE(Riesgos!$Q$2:$Q$151,2),Riesgos!$Q$2:$Q$151,0)) -> Explotación de vulnerabilidades conocidas | G7: =INDEX(Riesgos!$H$2:$H$151,MATCH(LARGE(Riesgos!$Q$2:$Q$151,2),Riesgos!$Q$2:$Q$151,0)) -> 4 | H7: =INDEX(Riesgos!$I$2:$I$151,MATCH(LARGE(Riesgos!$Q$2:$Q$151,2),Riesgos!$Q$2:$Q$151,0)) -> 4 | I7: =INDEX(Riesgos!$J$2:$J$151,MATCH(LARGE(Riesgos!$Q$2:$Q$151,2),Riesgos!$Q$2:$Q$151,0)) -> 16 | J7: =INDEX(Riesgos!$K$2:$K$151,MATCH(LARGE(Riesgos!$Q$2:$Q$151,2),Riesgos!$Q$2:$Q$151,0)) -> Alto | K7: =INDEX(Riesgos!$M$2:$M$151,MATCH(LARGE(Riesgos!$Q$2:$Q$151,2),Riesgos!$Q$2:$Q$151,0)) -> 16 | L7: =INDEX(Riesgos!$N$2:$N$151,MATCH(LARGE(Riesgos!$Q$2:$Q$151,2),Riesgos!$Q$2:$Q$151,0)) -> Alto | M7: =INDEX(Riesgos!$O$2:$O$151,MATCH(LARGE(Riesgos!$Q$2:$Q$151,2),Riesgos!$Q$2:$Q$151,0)) -> Reducir/Mitigar
B8: 3 | C8: =INDEX(Riesgos!$B$2:$B$151,MATCH(LARGE(Riesgos!$Q$2:$Q$151,3),Riesgos!$Q$2:$Q$151,0)) -> Producción | D8: =INDEX(Riesgos!$D$2:$D$151,MATCH(LARGE(Riesgos!$Q$2:$Q$151,3),Riesgos!$Q$2:$Q$151,0)) -> Servidor de Base de Datos | E8: =INDEX(Riesgos!$E$2:$E$151,MATCH(LARGE(Riesgos!$Q$2:$Q$151,3),Riesgos!$Q$2:$Q$151,0)) -> Concientización y Procesos | F8: =INDEX(Riesgos!$G$2:$G$151,MATCH(LARGE(Riesgos!$Q$2:$Q$151,3),Riesgos!$Q$2:$Q$151,0)) -> Explotación de vulnerabilidades no corregidas | G8: =INDEX(Riesgos!$H$2:$H$151,MATCH(LARGE(Riesgos!$Q$2:$Q$151,3),Riesgos!$Q$2:$Q$151,0)) -> 4 | H8: =INDEX(Riesgos!$I$2:$I$151,MATCH(LARGE(Riesgos!$Q$2:$Q$151,3),Riesgos!$Q$2:$Q$151,0)) -> 4 | I8: =INDEX(Riesgos!$J$2:$J$151,MATCH(LARGE(Riesgos!$Q$2:$Q$151,3),Riesgos!$Q$2:$Q$151,0)) -> 16 | J8: =INDEX(Riesgos!$K$2:$K$151,MATCH(LARGE(Riesgos!$Q$2:$Q$151,3),Riesgos!$Q$2:$Q$151,0)) -> Alto | K8: =INDEX(Riesgos!$M$2:$M$151,MATCH(LARGE(Riesgos!$Q$2:$Q$151,3),Riesgos!$Q$2:$Q$151,0)) -> 16 | L8: =INDEX(Riesgos!$N$2:$N$151,MATCH(LARGE(Riesgos!$Q$2:$Q$151,3),Riesgos!$Q$2:$Q$151,0)) -> Alto | M8: =INDEX(Riesgos!$O$2:$O$151,MATCH(LARGE(Riesgos!$Q$2:$Q$151,3),Riesgos!$Q$2:$Q$151,0)) -> Reducir/Mitigar
B9: 4 | C9: =INDEX(Riesgos!$B$2:$B$151,MATCH(LARGE(Riesgos!$Q$2:$Q$151,4),Riesgos!$Q$2:$Q$151,0)) -> Pruebas | D9: =INDEX(Riesgos!$D$2:$D$151,MATCH(LARGE(Riesgos!$Q$2:$Q$151,4),Riesgos!$Q$2:$Q$151,0)) -> Servidor de pruebas | E9: =INDEX(Riesgos!$E$2:$E$151,MATCH(LARGE(Riesgos!$Q$2:$Q$151,4),Riesgos!$Q$2:$Q$151,0)) -> Seguridad Perimetral | F9: =INDEX(Riesgos!$G$2:$G$151,MATCH(LARGE(Riesgos!$Q$2:$Q$151,4),Riesgos!$Q$2:$Q$151,0)) -> Ataques de fuerza bruta desde internet | G9: =INDEX(Riesgos!$H$2:$H$151,MATCH(LARGE(Riesgos!$Q$2:$Q$151,4),Riesgos!$Q$2:$Q$151,0)) -> 4 | H9: =INDEX(Riesgos!$I$2:$I$151,MATCH(LARGE(Riesgos!$Q$2:$Q$151,4),Riesgos!$Q$2:$Q$151,0)) -> 4 | I9: =INDEX(Riesgos!$J$2:$J$151,MATCH(LARGE(Riesgos!$Q$2:$Q$151,4),Riesgos!$Q$2:$Q$151,0)) -> 16 | J9: =INDEX(Riesgos!$K$2:$K$151,MATCH(LARGE(Riesgos!$Q$2:$Q$151,4),Riesgos!$Q$2:$Q$151,0)) -> Alto | K9: =INDEX(Riesgos!$M$2:$M$151,MATCH(LARGE(Riesgos!$Q$2:$Q$151,4),Riesgos!$Q$2:$Q$151,0)) -> 10 | L9: =INDEX(Riesgos!$N$2:$N$151,MATCH(LARGE(Riesgos!$Q$2:$Q$151,4),Riesgos!$Q$2:$Q$151,0)) -> Moderado | M9: =INDEX(Riesgos!$O$2:$O$151,MATCH(LARGE(Riesgos!$Q$2:$Q$151,4),Riesgos!$Q$2:$Q$151,0)) -> Reducir/Mitigar
B10: 5 | C10: =INDEX(Riesgos!$B$2:$B$151,MATCH(LARGE(Riesgos!$Q$2:$Q$151,5),Riesgos!$Q$2:$Q$151,0)) -> Pruebas | D10: =INDEX(Riesgos!$D$2:$D$151,MATCH(LARGE(Riesgos!$Q$2:$Q$151,5),Riesgos!$Q$2:$Q$151,0)) -> Herramienta de automatización de pruebas | E10: =INDEX(Riesgos!$E$2:$E$151,MATCH(LARGE(Riesgos!$Q$2:$Q$151,5),Riesgos!$Q$2:$Q$151,0)) -> Seguridad de Aplicación | F10: =INDEX(Riesgos!$G$2:$G$151,MATCH(LARGE(Riesgos!$Q$2:$Q$151,5),Riesgos!$Q$2:$Q$151,0)) -> Exposición de credenciales de otros sistemas | G10: =INDEX(Riesgos!$H$2:$H$151,MATCH(LARGE(Riesgos!$Q$2:$Q$151,5),Riesgos!$Q$2:$Q$151,0)) -> 4 | H10: =INDEX(Riesgos!$I$2:$I$151,MATCH(LARGE(Riesgos!$Q$2:$Q$151,5),Riesgos!$Q$2:$Q$151,0)) -> 4 | I10: =INDEX(Riesgos!$J$2:$J$151,MATCH(LARGE(Riesgos!$Q$2:$Q$151,5),Riesgos!$Q$2:$Q$151,0)) -> 16 | J10: =INDEX(Riesgos!$K$2:$K$151,MATCH(LARGE(Riesgos!$Q$2:$Q$151,5),Riesgos!$Q$2:$Q$151,0)) -> Alto | K10: =INDEX(Riesgos!$M$2:$M$151,MATCH(LARGE(Riesgos!$Q$2:$Q$151,5),Riesgos!$Q$2:$Q$151,0)) -> 10 | L10: =INDEX(Riesgos!$N$2:$N$151,MATCH(LARGE(Riesgos!$Q$2:$Q$151,5),Riesgos!$Q$2:$Q$151,0)) -> Moderado | M10: =INDEX(Riesgos!$O$2:$O$151,MATCH(LARGE(Riesgos!$Q$2:$Q$151,5),Riesgos!$Q$2:$Q$151,0)) -> Reducir/Mitigar
B11: 6 | C11: =INDEX(Riesgos!$B$2:$B$151,MATCH(LARGE(Riesgos!$Q$2:$Q$151,6),Riesgos!$Q$2:$Q$151,0)) -> Desarrollo | D11: =INDEX(Riesgos!$D$2:$D$151,MATCH(LARGE(Riesgos!$Q$2:$Q$151,6),Riesgos!$Q$2:$Q$151,0)) -> Código fuente y credenciales | E11: =INDEX(Riesgos!$E$2:$E$151,MATCH(LARGE(Riesgos!$Q$2:$Q$151,6),Riesgos!$Q$2:$Q$151,0)) -> Seguridad de Host | F11: =INDEX(Riesgos!$G$2:$G$151,MATCH(LARGE(Riesgos!$Q$2:$Q$151,6),Riesgos!$Q$2:$Q$151,0)) -> Robo de credenciales desde archivos locales | G11: =INDEX(Riesgos!$H$2:$H$151,MATCH(LARGE(Riesgos!$Q$2:$Q$151,6),Riesgos!$Q$2:$Q$151,0)) -> 4 | H11: =INDEX(Riesgos!$I$2:$I$151,MATCH(LARGE(Riesgos!$Q$2:$Q$151,6),Riesgos!$Q$2:$Q$151,0)) -> 4 | I11: =INDEX(Riesgos!$J$2:$J$151,MATCH(LARGE(Riesgos!$Q$2:$Q$151,6),Riesgos!$Q$2:$Q$151,0)) -> 16 | J11: =INDEX(Riesgos!$K$2:$K$151,MATCH(LARGE(Riesgos!$Q$2:$Q$151,6),Riesgos!$Q$2:$Q$151,0)) -> Alto | K11: =INDEX(Riesgos!$M$2:$M$151,MATCH(LARGE(Riesgos!$Q$2:$Q$151,6),Riesgos!$Q$2:$Q$151,0)) -> 10 | L11: =INDEX(Riesgos!$N$2:$N$151,MATCH(LARGE(Riesgos!$Q$2:$Q$151,6),Riesgos!$Q$2:$Q$151,0)) -> Moderado | M11: =INDEX(Riesgos!$O$2:$O$151,MATCH(LARGE(Riesgos!$Q$2:$Q$151,6),Riesgos!$Q$2:$Q$151,0)) -> Reducir/Mitigar
B12: 7 | C12: =INDEX(Riesgos!$B$2:$B$151,MATCH(LARGE(Riesgos!$Q$2:$Q$151,7),Riesgos!$Q$2:$Q$151,0)) -> Desarrollo | D12: =INDEX(Riesgos!$D$2:$D$151,MATCH(LARGE(Riesgos!$Q$2:$Q$151,7),Riesgos!$Q$2:$Q$151,0)) -> Desarrollador | E12: =INDEX(Riesgos!$E$2:$E$151,MATCH(LARGE(Riesgos!$Q$2:$Q$151,7),Riesgos!$Q$2:$Q$151,0)) -> Seguridad de Aplicación | F12: =INDEX(Riesgos!$G$2:$G$151,MATCH(LARGE(Riesgos!$Q$2:$Q$151,7),Riesgos!$Q$2:$Q$151,0)) -> Introducción de vulnerabilidades en el software desarrollado | G12: =INDEX(Riesgos!$H$2:$H$151,MATCH(LARGE(Riesgos!$Q$2:$Q$151,7),Riesgos!$Q$2:$Q$151,0)) -> 4 | H12: =INDEX(Riesgos!$I$2:$I$151,MATCH(LARGE(Riesgos!$Q$2:$Q$151,7),Riesgos!$Q$2:$Q$151,0)) -> 4 | I12: =INDEX(Riesgos!$J$2:$J$151,MATCH(LARGE(Riesgos!$Q$2:$Q$151,7),Riesgos!$Q$2:$Q$151,0)) -> 16 | J12: =INDEX(Riesgos!$K$2:$K$151,MATCH(LARGE(Riesgos!$Q$2:$Q$151,7),Riesgos!$Q$2:$Q$151,0)) -> Alto | K12: =INDEX(Riesgos!$M$2:$M$151,MATCH(LARGE(Riesgos!$Q$2:$Q$151,7),Riesgos!$Q$2:$Q$151,0)) -> 10 | L12: =INDEX(Riesgos!$N$2:$N$151,MATCH(LARGE(Riesgos!$Q$2:$Q$151,7),Riesgos!$Q$2:$Q$151,0)) -> Moderado | M12: =INDEX(Riesgos!$O$2:$O$151,MATCH(LARGE(Riesgos!$Q$2:$Q$151,7),Riesgos!$Q$2:$Q$151,0)) -> Reducir/Mitigar
B13: 8 | C13: =INDEX(Riesgos!$B$2:$B$151,MATCH(LARGE(Riesgos!$Q$2:$Q$151,8),Riesgos!$Q$2:$Q$151,0)) -> Producción | D13: =INDEX(Riesgos!$D$2:$D$151,MATCH(LARGE(Riesgos!$Q$2:$Q$151,8),Riesgos!$Q$2:$Q$151,0)) -> Servidor de Base de Datos | E13: =INDEX(Riesgos!$E$2:$E$151,MATCH(LARGE(Riesgos!$Q$2:$Q$151,8),Riesgos!$Q$2:$Q$151,0)) -> Seguridad de Red | F13: =INDEX(Riesgos!$G$2:$G$151,MATCH(LARGE(Riesgos!$Q$2:$Q$151,8),Riesgos!$Q$2:$Q$151,0)) -> Acceso remoto no autorizado | G13: =INDEX(Riesgos!$H$2:$H$151,MATCH(LARGE(Riesgos!$Q$2:$Q$151,8),Riesgos!$Q$2:$Q$151,0)) -> 3 | H13: =INDEX(Riesgos!$I$2:$I$151,MATCH(LARGE(Riesgos!$Q$2:$Q$151,8),Riesgos!$Q$2:$Q$151,0)) -> 5 | I13: =INDEX(Riesgos!$J$2:$J$151,MATCH(LARGE(Riesgos!$Q$2:$Q$151,8),Riesgos!$Q$2:$Q$151,0)) -> 15 | J13: =INDEX(Riesgos!$K$2:$K$151,MATCH(LARGE(Riesgos!$Q$2:$Q$151,8),Riesgos!$Q$2:$Q$151,0)) -> Alto | K13: =INDEX(Riesgos!$M$2:$M$151,MATCH(LARGE(Riesgos!$Q$2:$Q$151,8),Riesgos!$Q$2:$Q$151,0)) -> 15 | L13: =INDEX(Riesgos!$N$2:$N$151,MATCH(LARGE(Riesgos!$Q$2:$Q$151,8),Riesgos!$Q$2:$Q$151,0)) -> Alto | M13: =INDEX(Riesgos!$O$2:$O$151,MATCH(LARGE(Riesgos!$Q$2:$Q$151,8),Riesgos!$Q$2:$Q$151,0)) -> Reducir/Mitigar
B14: 9 | C14: =INDEX(Riesgos!$B$2:$B$151,MATCH(LARGE(Riesgos!$Q$2:$Q$151,9),Riesgos!$Q$2:$Q$151,0)) -> Producción | D14: =INDEX(Riesgos!$D$2:$D$151,MATCH(LARGE(Riesgos!$Q$2:$Q$151,9),Riesgos!$Q$2:$Q$151,0)) -> Servidor de Base de Datos | E14: =INDEX(Riesgos!$E$2:$E$151,MATCH(LARGE(Riesgos!$Q$2:$Q$151,9),Riesgos!$Q$2:$Q$151,0)) -> Seguridad de Aplicación | F14: =INDEX(Riesgos!$G$2:$G$151,MATCH(LARGE(Riesgos!$Q$2:$Q$151,9),Riesgos!$Q$2:$Q$151,0)) -> Inyección SQL / escalamiento de privilegios | G14: =INDEX(Riesgos!$H$2:$H$151,MATCH(LARGE(Riesgos!$Q$2:$Q$151,9),Riesgos!$Q$2:$Q$151,0)) -> 3 | H14: =INDEX(Riesgos!$I$2:$I$151,MATCH(LARGE(Riesgos!$Q$2:$Q$151,9),Riesgos!$Q$2:$Q$151,0)) -> 5 | I14: =INDEX(Riesgos!$J$2:$J$151,MATCH(LARGE(Riesgos!$Q$2:$Q$151,9),Riesgos!$Q$2:$Q$151,0)) -> 15 | J14: =INDEX(Riesgos!$K$2:$K$151,MATCH(LARGE(Riesgos!$Q$2:$Q$151,9),Riesgos!$Q$2:$Q$151,0)) -> Alto | K14: =INDEX(Riesgos!$M$2:$M$151,MATCH(LARGE(Riesgos!$Q$2:$Q$151,9),Riesgos!$Q$2:$Q$151,0)) -> 15 | L14: =INDEX(Riesgos!$N$2:$N$151,MATCH(LARGE(Riesgos!$Q$2:$Q$151,9),Riesgos!$Q$2:$Q$151,0)) -> Alto | M14: =INDEX(Riesgos!$O$2:$O$151,MATCH(LARGE(Riesgos!$Q$2:$Q$151,9),Riesgos!$Q$2:$Q$151,0)) -> Reducir/Mitigar
B15: 10 | C15: =INDEX(Riesgos!$B$2:$B$151,MATCH(LARGE(Riesgos!$Q$2:$Q$151,10),Riesgos!$Q$2:$Q$151,0)) -> Producción | D15: =INDEX(Riesgos!$D$2:$D$151,MATCH(LARGE(Riesgos!$Q$2:$Q$151,10),Riesgos!$Q$2:$Q$151,0)) -> Servidor de Base de Datos | E15: =INDEX(Riesgos!$E$2:$E$151,MATCH(LARGE(Riesgos!$Q$2:$Q$151,10),Riesgos!$Q$2:$Q$151,0)) -> Seguridad de Datos | F15: =INDEX(Riesgos!$G$2:$G$151,MATCH(LARGE(Riesgos!$Q$2:$Q$151,10),Riesgos!$Q$2:$Q$151,0)) -> Fuga de información confidencial | G15: =INDEX(Riesgos!$H$2:$H$151,MATCH(LARGE(Riesgos!$Q$2:$Q$151,10),Riesgos!$Q$2:$Q$151,0)) -> 3 | H15: =INDEX(Riesgos!$I$2:$I$151,MATCH(LARGE(Riesgos!$Q$2:$Q$151,10),Riesgos!$Q$2:$Q$151,0)) -> 5 | I15: =INDEX(Riesgos!$J$2:$J$151,MATCH(LARGE(Riesgos!$Q$2:$Q$151,10),Riesgos!$Q$2:$Q$151,0)) -> 15 | J15: =INDEX(Riesgos!$K$2:$K$151,MATCH(LARGE(Riesgos!$Q$2:$Q$151,10),Riesgos!$Q$2:$Q$151,0)) -> Alto | K15: =INDEX(Riesgos!$M$2:$M$151,MATCH(LARGE(Riesgos!$Q$2:$Q$151,10),Riesgos!$Q$2:$Q$151,0)) -> 15 | L15: =INDEX(Riesgos!$N$2:$N$151,MATCH(LARGE(Riesgos!$Q$2:$Q$151,10),Riesgos!$Q$2:$Q$151,0)) -> Alto | M15: =INDEX(Riesgos!$O$2:$O$151,MATCH(LARGE(Riesgos!$Q$2:$Q$151,10),Riesgos!$Q$2:$Q$151,0)) -> Reducir/Mitigar
